{
	"lastBuildDate":"Wed, 13 Sep 2023 06:10:02 +0900",
	"total":209426,
	"start":1,
	"display":30,
	"items":[
		{
			"title":"&quot;곧 가을 이사철인데&quot;…전셋값 상승세 수도권 전역으로 확산",
			"originallink":"http:\/\/www.newsis.com\/view\/?id=NISX20230912_0002447383&cID=10401&pID=10400",
			"link":"https:\/\/n.news.naver.com\/mnews\/article\/003\/0012086073?sid=101",
			"description":"경기도는 의왕시와 용인시, 안산시 등이 7월에 이어 두 달 연속 상승세를 이어갔고, 인천은 서구 <b>청라<\/b>와 연수구 송도국제도시를 중심으로 상승했다. 올해 1~7월까지 수도권 전세 거래 누계 건수는 9만4413건으로 지난해... ",
			"pubDate":"Wed, 13 Sep 2023 06:02:00 +0900"
		},
		{
			"title":"인천경제청, 송도국제도시에 '글로벌 특화병원' 유치 추진",
			"originallink":"https:\/\/www.cstimes.com\/news\/articleView.html?idxno=560118",
			"link":"https:\/\/www.cstimes.com\/news\/articleView.html?idxno=560118",
			"description":"또 IFEZ(인천경제자유구역)에 송도세브란스병원과 <b>청라<\/b>아산병원 등 각각 800병상 규모의 대형 종합병원이... 김진용 청장은 &quot;글로벌 특화병원은 국제병원 부지를 더 이상 나대지로 놔둘 수 없고 송도세브란스병원·<b>청라<\/b>아... ",
			"pubDate":"Wed, 13 Sep 2023 01:14:00 +0900"
		},
		{
			"title":"송도국제도시에 글로벌 특화병원 유치 추진",
			"originallink":"https:\/\/www.kmaeil.com\/news\/articleView.html?idxno=416352",
			"link":"https:\/\/www.kmaeil.com\/news\/articleView.html?idxno=416352",
			"description":"또 IFEZ(인천경제자유구역)에 송도세브란스병원과 <b>청라<\/b>아산병원 등 각각 800병상 규모의 대형 종합병원이... 김진용 청장은 &quot;글로벌 특화병원은 국제병원 부지를 더 이상 나대지로 놔둘 수 없고 송도세브란스병원·<b>청라<\/b>아... ",
			"pubDate":"Tue, 12 Sep 2023 23:52:00 +0900"
		},
		{
			"title":"인천경제청, 성광의료재단과 송도국제도시 글로벌 특화병원 유치 양해각서 체...",
			"originallink":"https:\/\/ilyo.co.kr\/?ac=article_view&entry_id=458905",
			"link":"https:\/\/ilyo.co.kr\/?ac=article_view&entry_id=458905",
			"description":"또 IFEZ(인천경제자유구역)에 송도세브란스병원과 <b>청라<\/b>아산병원 등 각각 800병상 규모의 대형 종합병원이... 김진용 청장은 &quot;글로벌 특화병원은 국제병원 부지를 더 이상 나대지로 놔둘 수 없고 송도세브란스병원·<b>청라<\/b>아... ",
			"pubDate":"Tue, 12 Sep 2023 23:20:00 +0900"
		},
		{
			"title":"인천서구 2025 APEC 정상회의, 인천고등법원 해사전문법원 인천 유치 위한 출...",
			"originallink":"https:\/\/www.kmaeil.com\/news\/articleView.html?idxno=416347",
			"link":"https:\/\/www.kmaeil.com\/news\/articleView.html?idxno=416347",
			"description":"지난 달 17일 검단사거리역과 완정역을 시작으로 29일 석남역과 가정역, 이번 달 7일 <b>청라<\/b>국제도시역과 검암역에 이어 마지막으로 진행하는 홍보 캠페인이다. 가좌동 건지사거리의 많은 사람들이 홍보 캠페인에... ",
			"pubDate":"Tue, 12 Sep 2023 23:02:00 +0900"
		},
		{
			"title":"인천경제청, 송도국제도시에 글로벌 특화병원 유치 추진",
			"originallink":"https:\/\/www.kmaeil.com\/news\/articleView.html?idxno=416336",
			"link":"https:\/\/www.kmaeil.com\/news\/articleView.html?idxno=416336",
			"description":"또 IFEZ(인천경제자유구역)에 송도세브란스병원과 <b>청라<\/b>아산병원 등 각각 800병상 규모의 대형 종합병원이... 김진용 청장은 &quot;글로벌 특화병원은 국제병원 부지를 더 이상 나대지로 놔둘 수 없고 송도세브란스병원·<b>청라<\/b>아... ",
			"pubDate":"Tue, 12 Sep 2023 22:02:00 +0900"
		},
		{
			"title":"송도국제병원 터 10년 만에 '차병원' 안착",
			"originallink":"http:\/\/www.kihoilbo.co.kr\/news\/articleView.html?idxno=1049034",
			"link":"http:\/\/www.kihoilbo.co.kr\/news\/articleView.html?idxno=1049034",
			"description":"김진용 인천경제청장은 &quot;글로벌 특화병원은 국제병원 부지를 더 이상 나대지로 놔둬서는 안 되는 상황인 데다, IFEZ 안에 송도세브란스병원과 <b>청라<\/b>아산병원을 추진 중인 가운데 세포치료, 안티 에이징, 난임 같은 미래... ",
			"pubDate":"Tue, 12 Sep 2023 21:18:00 +0900"
		},
		{
			"title":"'상암DMC 랜드마크 개발' 주목… 인천 권역별 자원순환센터 해법 찾기",
			"originallink":"http:\/\/www.kyeongin.com\/main\/view.php?key=20230912010002298",
			"link":"http:\/\/www.kyeongin.com\/main\/view.php?key=20230912010002298",
			"description":"사진은 현재 인천에서 운영 중인 <b>청라<\/b>소각장. \/경인일보DB  인천시가 지지부진한 권역별 자원순환센터(소각시설) 조성과 개발사업·앵커시설 유치 등 지역 현안 해결책 제시를 연계해 돌파구를 찾을지 관심이 쏠린다.12일... ",
			"pubDate":"Tue, 12 Sep 2023 21:00:00 +0900"
		},
		{
			"title":"인천 송도국제도시에 '난임·항노화 글로벌 특화병원' 만든다",
			"originallink":"http:\/\/www.joongboo.com\/news\/articleView.html?idxno=363610873",
			"link":"http:\/\/www.joongboo.com\/news\/articleView.html?idxno=363610873",
			"description":"김진용 청장은 &quot;글로벌 특화병원은 국제병원 부지를 더 이상 나대지로 놔둘 수 없고 송도세브란스병원·<b>청라<\/b>아산병원 등이 추진중인 상황에서 세포치료, 안티 에이징, 난임 등 미래 의료 트렌드에 초점을 맞춰 추진되는... ",
			"pubDate":"Tue, 12 Sep 2023 20:56:00 +0900"
		},
		{
			"title":"특혜 잡음 <b>청라<\/b>영상단지, 경찰 수사 본격화 조짐",
			"originallink":"https:\/\/www.incheonilbo.com\/news\/articleView.html?idxno=1211420",
			"link":"https:\/\/www.incheonilbo.com\/news\/articleView.html?idxno=1211420",
			"description":"▲ <b>청라<\/b>영상문화복합단지 조감도. \/인천일보DB 사업자 선정 과정에서 '불공정·부실 심사' 논란이 일었던 인천경제청의 '<b>청라<\/b> 영상·문화복합단지' 공모 사업에 대해 경찰이 수사에 나설지 주목된다. 경찰이 해당 의혹과... ",
			"pubDate":"Tue, 12 Sep 2023 20:12:00 +0900"
		},
		{
			"title":"[인천경제청·성광의료재단 양해각서] 20년 황무지, 이번엔 '차병원' 눈독",
			"originallink":"https:\/\/www.incheonilbo.com\/news\/articleView.html?idxno=1211427",
			"link":"https:\/\/www.incheonilbo.com\/news\/articleView.html?idxno=1211427",
			"description":"차병원은 앞서 <b>청라<\/b>의료복합타운 공모에서 서울아산병원에 밀려 고배를 마셨다. 김진용 인천경제자유구역청장은 &quot;국제병원 부지를 더 이상 나대지로 놔줄 수 없고, 송도세브란스병원·<b>청라<\/b>아산병원 등이 추진 중인... ",
			"pubDate":"Tue, 12 Sep 2023 20:12:00 +0900"
		},
		{
			"title":"송도 국제병원 부지에 차병원 설립 추진",
			"originallink":"https:\/\/www.incheonilbo.com\/news\/articleView.html?idxno=1211403",
			"link":"https:\/\/www.incheonilbo.com\/news\/articleView.html?idxno=1211403",
			"description":"인천경제자유구역청은 송도세브란스병원·<b>청라<\/b>아산병원이 들어서는 현실을 고려해 세포·항노화·난임... 인천경제자유구역에선 송도세브란스병원·<b>청라<\/b>아산병원이 각각 800병상 규모 종합병원으로 설립될 예정이다.... ",
			"pubDate":"Tue, 12 Sep 2023 20:12:00 +0900"
		},
		{
			"title":"<b>청라<\/b>~강서 7700번 버스 이용객 '만족'",
			"originallink":"https:\/\/www.incheonilbo.com\/news\/articleView.html?idxno=1211370",
			"link":"https:\/\/www.incheonilbo.com\/news\/articleView.html?idxno=1211370",
			"description":"인천 <b>청라<\/b>국제도시와 서울 강서구를 오가는 광역 간선급행버스(BRT)인 7700번을 이용하는 시민들이 대부분... 특히 이용객의 95%는 기존 노선(<b>청라<\/b>~가양)을 <b>청라<\/b>~화곡으로 단축한 것에 만족한다고 답했으며, 응답자의... ",
			"pubDate":"Tue, 12 Sep 2023 18:48:00 +0900"
		},
		{
			"title":"줄기세포·안티에이징·난임 전문치료… 인천 송도에 '글로벌 특화병원' 추진",
			"originallink":"https:\/\/www.sedaily.com\/NewsView\/29UNMBUX2P",
			"link":"https:\/\/n.news.naver.com\/mnews\/article\/011\/0004237513?sid=102",
			"description":"김진용 인천경제청장은 &quot;앞으로 송도세브란스병원과 <b>청라<\/b>아산병원 등 종합병원이 건립되는 점을 고려해 특화병원 유치를 추진하게 됐다&quot;며 &quot;사업을 차질 없이 추진해 송도 활성화에 기여하겠다&quot;고 말했다.",
			"pubDate":"Tue, 12 Sep 2023 18:21:00 +0900"
		},
		{
			"title":"송도국제도시에 글로벌 특화병원 추진 (B tv 인천뉴스)",
			"originallink":"http:\/\/ch1.skbroadband.com\/content\/view?parent_no=24&content_no=58&p_no=161524",
			"link":"http:\/\/ch1.skbroadband.com\/content\/view?parent_no=24&content_no=58&p_no=161524",
			"description":"현재 인천경제자유구역에는 송도세브란스병원과 <b>청라<\/b>아산병원 등 대형 종합병원이 추진 중입니다. 이 때문에 대형 종합병원 유치는 한계가 있어, 특화된 중소형 종합병원을 유치하기로 했다는 게 경제청... ",
			"pubDate":"Tue, 12 Sep 2023 18:16:00 +0900"
		},
		{
			"title":"인천 송도 ‘항노화·난임 치료’ 메카",
			"originallink":"http:\/\/www.fnnews.com\/news\/202309121811007192",
			"link":"https:\/\/n.news.naver.com\/mnews\/article\/014\/0005071506?sid=102",
			"description":"또 인천에는 인하대병원과 가천길병원이 이미 운영 중이고 송도에 세브란스병원과 <b>청라<\/b>에 아산병원이 각각 800병상 규모의 대형 종합병원이 건립을 추진 중이다. 인천경제청은 현재 상황에서 대형 종합병원 유치는... ",
			"pubDate":"Tue, 12 Sep 2023 18:12:00 +0900"
		},
		{
			"title":"인천경제청, 송도국제도시에 글로벌 특화병원 유치 추진",
			"originallink":"https:\/\/www.ajunews.com\/view\/20230912163313705",
			"link":"https:\/\/www.ajunews.com\/view\/20230912163313705",
			"description":"또 IFEZ(인천경제자유구역)에 송도세브란스병원과 <b>청라<\/b>아산병원 등 각각 800병상 규모의 대형 종합병원이... 송도세브란스병원·<b>청라<\/b>아산병원 등이 추진중인 상황에서 세포치료, 안티 에이징, 난임 등 미래 의료... ",
			"pubDate":"Tue, 12 Sep 2023 17:40:00 +0900"
		},
		{
			"title":"인천경제청-차병원 MOU··· 송도국제도시에 ‘글로벌 특화병원’",
			"originallink":"https:\/\/www.siminilbo.co.kr\/news\/newsview.php?ncode=1160288058057062",
			"link":"https:\/\/www.siminilbo.co.kr\/news\/newsview.php?ncode=1160288058057062",
			"description":"김진용 인천경제청장은 “글로벌 특화병원은 국제병원 부지를 더 이상 나대지로 놔둘 수 없고 송도세브란스병원ㆍ<b>청라<\/b>아산병원 등이 추진중인 상황에서 세포치료, 안티 에이징, 난임 등 미래 의료 트렌드에 초점을... ",
			"pubDate":"Tue, 12 Sep 2023 17:28:00 +0900"
		},
		{
			"title":"미래산업 혁신도시 인천…연구개발 투자는 꼴찌?",
			"originallink":"http:\/\/www.ifm.kr\/news\/368895",
			"link":"http:\/\/www.ifm.kr\/news\/368895",
			"description":"&lt;기자&gt; 바이오 도시 송도, 로봇과 의료 도시 <b>청라<\/b>, 항공MRO 특화도시 영종. 각종 첨단산업을 앞세운 화려한 면면과 달리 내실은 부족했습니다. 재작년 기준 인천시가 연구개발 분야에 투자한 예산은 국비를 합쳐 모두... ",
			"pubDate":"Tue, 12 Sep 2023 17:22:00 +0900"
		},
		{
			"title":"모리셔스브라운-지노베타케어 이색 콜라보 진행 중",
			"originallink":"https:\/\/news.kmib.co.kr\/article\/view.asp?arcid=0018661097&code=61122011&cp=nv",
			"link":"https:\/\/n.news.naver.com\/mnews\/article\/005\/0001637586?sid=102",
			"description":"앞서 지난달 23일에는 지노베타케어 ‘모이스처라이저’ 카렌듈라 신제품 런칭을 기념한 네이버 라이브 방송을 모리셔스브라운 인천 <b>청라<\/b>점 현장에서 콜라보 방송으로 진행해 시청자들의 큰 관심을 끌었다. 특히 이달... ",
			"pubDate":"Tue, 12 Sep 2023 17:13:00 +0900"
		},
		{
			"title":"인천 서구, 가좌동서 APEC 등 유치 캠페인",
			"originallink":"http:\/\/www.shinailbo.co.kr\/news\/articleView.html?idxno=1758939",
			"link":"http:\/\/www.shinailbo.co.kr\/news\/articleView.html?idxno=1758939",
			"description":"지난달 17일 검단사거리역과 완정역을 시작으로 29일 석남역과 가정역, 이번 달 7일 <b>청라<\/b>국제도시역과 검암역에 이어 마지막으로 진행하는 홍보 캠페인이다. 이날 가좌동 건지사거리의 많은 사람들이 홍보 캠페인에... ",
			"pubDate":"Tue, 12 Sep 2023 16:48:00 +0900"
		},
		{
			"title":"인천시-주한외국상의·코트라, 라운드테이블 개최…'뉴홍콩시티' 투자유치 협...",
			"originallink":"https:\/\/view.asiae.co.kr\/article\/2023091216463775201",
			"link":"https:\/\/n.news.naver.com\/mnews\/article\/277\/0005313221?sid=102",
			"description":"뉴홍콩시티는 송도·<b>청라<\/b>·영종 등 경제자유구역과 강화·옹진군, 인천 내항을 거점으로 최적의 비즈니스 환경을 조성하고 첨단산업을 육성하는 내용이다. 이를 위해 시는 인천이 강점을 지닌 바이오·반도체... ",
			"pubDate":"Tue, 12 Sep 2023 16:46:00 +0900"
		},
		{
			"title":"인천경제청, 송도국제도시에 글로벌 특화병원 유치 추진",
			"originallink":"https:\/\/www.eroun.net\/news\/articleView.html?idxno=37179",
			"link":"https:\/\/www.eroun.net\/news\/articleView.html?idxno=37179",
			"description":"또 IFEZ(인천경제자유구역)에 송도세브란스병원과 <b>청라<\/b>아산병원 등 각각 800병상 규모의 대형 종합병원이... 김진용 청장은 &quot;글로벌 특화병원은 국제병원 부지를 더 이상 나대지로 놔둘 수 없고 송도세브란스병원·<b>청라<\/b>아... ",
			"pubDate":"Tue, 12 Sep 2023 16:16:00 +0900"
		},
		{
			"title":"인천 서구, 2025 APEC 정상회의 등 인천 유치 위한 출근길 홍보 캠페인",
			"originallink":"http:\/\/www.joongboo.com\/news\/articleView.html?idxno=363610772",
			"link":"http:\/\/www.joongboo.com\/news\/articleView.html?idxno=363610772",
			"description":"이날 홍보활동은 지난 달 17일 검단사거리역과 완정역을 시작으로, 29일 석남역과 가정역, 이번 7일 <b>청라<\/b>국제도시역과 검암역에 이어 마지막으로 진행하는 홍보 캠페인이다. 가좌동 건지사거리의 많은 사람들이 홍보... ",
			"pubDate":"Tue, 12 Sep 2023 16:08:00 +0900"
		},
		{
			"title":"인천경제청-차병원, 송도에 글로벌 특화병원 유치",
			"originallink":"http:\/\/www.paxetv.com\/news\/articleView.html?idxno=185595",
			"link":"http:\/\/www.paxetv.com\/news\/articleView.html?idxno=185595",
			"description":"송도세브란스병원과 <b>청라<\/b>아산병원 등 각각 800병상 규모의 대형 종합병원이 유치돼 추진 중에 있습니다.... 김진용 청장은 &quot;글로벌 특화병원은 국제병원 부지를 더 이상 나대지로 놔둘 수 없고 송도세브란스병원·<b>청라<\/b>아... ",
			"pubDate":"Tue, 12 Sep 2023 16:08:00 +0900"
		},
		{
			"title":"인천교통공사, <b>청라<\/b>~강서 BRT(7700번) 이용만족도 96%",
			"originallink":"http:\/\/www.incheontoday.com\/news\/articleView.html?idxno=234412",
			"link":"http:\/\/www.incheontoday.com\/news\/articleView.html?idxno=234412",
			"description":"인천투데이=김갑봉 기자 | 인천 서구 <b>청라<\/b>지구와 서울 강서구 화곡동을 잇는 간선급행버스(BRT) 7700번... 특히, 인천 서구 <b>청라<\/b> ~ 서울 강서구 가양에서 <b>청라<\/b> ~ 화곡으로 노선을 조정하고, 좌석제를 도입한 부분에서... ",
			"pubDate":"Tue, 12 Sep 2023 16:04:00 +0900"
		},
		{
			"title":"<b>청라<\/b> 디에프이지움, 오피스텔 상가 투자시장 '꿈틀'",
			"originallink":"http:\/\/www.ikld.kr\/news\/articleView.html?idxno=280765",
			"link":"http:\/\/www.ikld.kr\/news\/articleView.html?idxno=280765",
			"description":"<b>청라<\/b>커낼웨이 수변을 바라보고 있는 <b>청라<\/b>디에프이지움의 분양이 시작됨과 동시에 많은 투자자들이 계약을 진행하고 있다. 교통, 문화, 공연, 쇼핑, 공원, 레저, 의료 등 수많은 호재거리가 즐비한 <b>청라<\/b>의 급부상으로 최근... ",
			"pubDate":"Tue, 12 Sep 2023 15:42:00 +0900"
		},
		{
			"title":"인천경제청, 글로벌 특화병원 유치 추진한다.",
			"originallink":"http:\/\/www.breaknews.com\/986923",
			"link":"http:\/\/www.breaknews.com\/986923",
			"description":"또 IFEZ(인천경제자유구역)에 송도세브란스병원과 <b>청라<\/b>아산병원 등 각각 800병상 규모의 대형 종합병원이 유치돼 추진 중이다. 인천경제청은 이에따라 현재... ",
			"pubDate":"Tue, 12 Sep 2023 15:38:00 +0900"
		},
		{
			"title":"인천경제청, 송도국제도시에 글로벌 특화병원 유치 추진",
			"originallink":"http:\/\/www.shinailbo.co.kr\/news\/articleView.html?idxno=1758855",
			"link":"http:\/\/www.shinailbo.co.kr\/news\/articleView.html?idxno=1758855",
			"description":"또한 인천경제자유구역(IFEZ)에 송도세브란스병원과 <b>청라<\/b>아산병원 등 각각 800병상 규모의 대형 종합병원이... 송도세브란스병원·<b>청라<\/b>아산병원 등이 추진중인 상황에서 세포치료, 안티 에이징, 난임 등 미래 의료... ",
			"pubDate":"Tue, 12 Sep 2023 15:36:00 +0900"
		},
		{
			"title":"정서진중앙시장, 인천 서구 관광지 체험단 초청...다양한 이벤트",
			"originallink":"https:\/\/www.ajunews.com\/view\/20230912151036586",
			"link":"https:\/\/www.ajunews.com\/view\/20230912151036586",
			"description":"주요 일정으로 <b>청라<\/b> 호수 공원에서 오리배를 탑승하고 <b>청라<\/b>생태공원에서 보물찾기를 진행했다. 녹정자 박물관을 방문해 머그컵 그림 그리기도 체험했다. 이후 정서진 아라뱃길·아라타워를 방문하기도 했다. 이후... ",
			"pubDate":"Tue, 12 Sep 2023 15:30:00 +0900"
		}
	]
}