{
	"lastBuildDate":"Thu, 26 Mar 2026 18:30:01 +0900",
	"total":291299,
	"start":1,
	"display":30,
	"items":[
		{
			"title":"이마트 “연내 6개 점포 스타필드 마켓으로 전환…글로벌 신규 국가 진...",
			"originallink":"https:\/\/byline.network\/?p=9004111222596500",
			"link":"https:\/\/byline.network\/?p=9004111222596500",
			"description":"이날 주총에서 한 주주는 스타필드 <b>청라<\/b>, 동서울 터미널, 화성 테마파크, AI 데이터 센터 등 투자에 따른 재무 안정성을 우려했다. 한 대표는 &quot;유통업은 현재 경쟁 심화와 성장 정체, 정부 규제 등으로 상당히 어려운... ",
			"pubDate":"Thu, 26 Mar 2026 18:04:00 +0900"
		},
		{
			"title":"연임 확정·배당 확대…4대 금융 주총 핵심은 '안정'",
			"originallink":"https:\/\/news.mtn.co.kr\/news-detail\/2026032616391731988",
			"link":"https:\/\/news.mtn.co.kr\/news-detail\/2026032616391731988",
			"description":"하나금융은 본점의 인천 <b>청라<\/b> 이전을 계기로 데이터센터와 본사 기능을 통합하는 구조 재편에 나섭니다. 내실을 택한 금융지주들이 디지털 전환과 사업 다각화로 성장 돌파구를 마련하는 동시에, 지배구조 개선과... ",
			"pubDate":"Thu, 26 Mar 2026 17:54:00 +0900"
		},
		{
			"title":"인천 집값 29주 만에 하락... 서구 매물 1만2천건까지 돌파",
			"originallink":"http:\/\/www.incheonin.com\/news\/articleView.html?idxno=116689",
			"link":"http:\/\/www.incheonin.com\/news\/articleView.html?idxno=116689",
			"description":"인천 서구 <b>청라<\/b>국제도시 전경. 사진=인천경제자유구역청 인천 아파트값이 반년 만에 하락 전환했다.... 자치구별로는 <b>청라<\/b>국제도시와 검단신도시, 루원시티 등 신도시가 밀집한 서구를 중심으로 하락세가... ",
			"pubDate":"Thu, 26 Mar 2026 17:44:00 +0900"
		},
		{
			"title":"[호르무즈 봉쇄 여파] ② 인천 외식업계 &quot;소비심리 위축...3월은 반등기...",
			"originallink":"https:\/\/news.ifm.kr\/news\/articleView.html?idxno=467681",
			"link":"https:\/\/news.ifm.kr\/news\/articleView.html?idxno=467681",
			"description":"박 회장은 &quot;<b>청라<\/b>·송도 2개 신도시는 관리비 문제도 심각하다&quot;며 &quot;원래 자영업들은 월세도 많이 내는데 상가 관리비마저 많이 나오는 상황&quot;이라고 했습니다. 이어 &quot;신도시엔 통상가(집합건물) 형태가 많은데, 이는 아예... ",
			"pubDate":"Thu, 26 Mar 2026 17:12:00 +0900"
		},
		{
			"title":"[내일 날씨] 서해안 새벽 비·짙은 안개…미세먼지 '나쁨'",
			"originallink":"http:\/\/www.joongang.tv\/news\/articleView.html?idxno=211419",
			"link":"http:\/\/www.joongang.tv\/news\/articleView.html?idxno=211419",
			"description":"특히 인천대교, 영종대교, <b>청라<\/b>하늘대교, 서해대교 등 해안 교량과 강·호수 주변 도로에서는 시야 확보가 어려워 교통안전에 각별한 주의가 필요하다. 짙은 안개로 인해 이슬비가 내리는 곳이 있겠고, 서쪽 지역... ",
			"pubDate":"Thu, 26 Mar 2026 16:52:00 +0900"
		},
		{
			"title":"[내일날씨] 큰 일교차 계속…내륙 낮 20도 안팎",
			"originallink":"https:\/\/www.topstarnews.net\/news\/articleView.html?idxno=16016948",
			"link":"https:\/\/www.topstarnews.net\/news\/articleView.html?idxno=16016948",
			"description":"특히 영종대교와 인천대교, <b>청라<\/b>하늘대교, 서해대교, 천사대교 등 해안 교량과 강·호수·골짜기 인접 도로는 주변보다 안개가 더 짙을 가능성이 커 출근 시간대 감속 운행이 필요하다. 짙은 안개로 이슬비가 내리는... ",
			"pubDate":"Thu, 26 Mar 2026 16:30:00 +0900"
		},
		{
			"title":"[내일의 날씨] 서쪽 200m 짙은 안개·수도권 5mm 미만 비…중부·경북 대...",
			"originallink":"https:\/\/www.topstarnews.net\/news\/articleView.html?idxno=16016949",
			"link":"https:\/\/www.topstarnews.net\/news\/articleView.html?idxno=16016949",
			"description":"특히, 해안에 위치한 '영종대교', '인천대교', '<b>청라<\/b>하늘대교', '서해대교', '천사대교' 등 교량과 내륙의 강이나 호수, 골짜기에 인접한 도로에서는 주변보다 안개가 더욱 짙게 끼면서, 일부 지역에서는 짙은 안개로 인해... ",
			"pubDate":"Thu, 26 Mar 2026 16:26:00 +0900"
		},
		{
			"title":"유정복 시장, 세계 최고 높이 전망대 품은 <b>청라<\/b>하늘대교 4월 개장 앞두고...",
			"originallink":"https:\/\/www.dnews.co.kr\/uhtml\/view.jsp?idxno=202603261457304520828",
			"link":"https:\/\/www.dnews.co.kr\/uhtml\/view.jsp?idxno=202603261457304520828",
			"description":"25일 <b>청라<\/b>하늘대교 관광시설 현장을 찾아 시설 운영 계획 및 안전 대책 등 개장 준비 상황을 면밀히 살폈다고 밝혔다. <b>청라<\/b>하늘대교 관광시설은 현재 막바지 공정이 진행 중이며, 오는 4월 정식 개장을 목표로 하고 있다.... ",
			"pubDate":"Thu, 26 Mar 2026 16:22:00 +0900"
		},
		{
			"title":"인천공항 품은 영종구 7월 출범…사통팔달 교통체계 구축",
			"originallink":"https:\/\/www.hankyung.com\/article\/2026032676931",
			"link":"https:\/\/n.news.naver.com\/mnews\/article\/015\/0005267411?sid=102",
			"description":"◇<b>청라<\/b>하늘대교 개통 올해 1월 <b>청라<\/b>하늘대교가 개통됐다. <b>청라<\/b>하늘대교는 영종국제도시와 서구 <b>청라<\/b>국제도시를 잇는 총연장 4.68㎞ 규모의 연륙교다. 영종·인천대교에 이어 인천 내륙과 영종을 직접 연결하는 세 번째... ",
			"pubDate":"Thu, 26 Mar 2026 16:08:00 +0900"
		},
		{
			"title":"[Invest]금융지주 회장 줄줄이 연임한 날…&quot;지배구조 강력 점검&quot; 재차 강...",
			"originallink":"https:\/\/www.investchosun.com\/site\/data\/html_dir\/2026\/03\/26\/2026032680170.html",
			"link":"https:\/\/www.investchosun.com\/site\/data\/html_dir\/2026\/03\/26\/2026032680170.html",
			"description":"하나금융은 이번 주총에서 본점 소재지를 서울 중구에서 인천 서구 <b>청라<\/b>국제도시로 변경하는 정관 개정안을 의결했다. 정관 변경 효력은 오는 9월 30일부터 발생하며, 이로써 하나금융의 본격적인 '<b>청라<\/b> 시대'가 열리게... ",
			"pubDate":"Thu, 26 Mar 2026 15:52:00 +0900"
		},
		{
			"title":"SK브로드밴드 인천방송, 1분기 시청자위원회 개최",
			"originallink":"https:\/\/news.skbroadband.com\/news\/articleView.html?idxno=222165",
			"link":"https:\/\/news.skbroadband.com\/news\/articleView.html?idxno=222165",
			"description":"상품 서비스 등 주요 사업 내용에 대한 보고를 받았습니다. 또 <b>청라<\/b>하늘대교 개통과 장애인 성폭행 사건이 발생한 색동원, 서울5호선 김포검단 연장선 등 심층 보도에 대한 내용을 청취하고, 이에 대한 의견을 나눴습니다.",
			"pubDate":"Thu, 26 Mar 2026 15:48:00 +0900"
		},
		{
			"title":"‘BMW’ 날고 ‘벤츠’ 추락...소비자 인식 바뀌었다",
			"originallink":"https:\/\/www.betanews.net\/article\/view\/beta202603260059",
			"link":"https:\/\/www.betanews.net\/article\/view\/beta202603260059",
			"description":"이 기간 벤츠는 국내 판매 대수 1위를 BMW에 빼앗겼고(2023년부터) 인천 <b>청라<\/b> 전기차 화재 사고(2024년 8월) 등 직접적인 악재가 잇따랐다. 이는 소셜 빅데이터 분석에서도 확인된다. ‘퀘타아이’를 활용한 빅데이터... ",
			"pubDate":"Thu, 26 Mar 2026 15:22:00 +0900"
		},
		{
			"title":"종량제 봉투 사재기 비상...인천시, 200일치 물량 확보·가격 인상 계획...",
			"originallink":"http:\/\/www.incheonnews.com\/news\/articleView.html?idxno=435045",
			"link":"http:\/\/www.incheonnews.com\/news\/articleView.html?idxno=435045",
			"description":"주변에서 다들 산다고 하길래 군중심리가 작용했나 보다.&quot; ＃인천 <b>청라<\/b> 주민 B씨 － &quot;친구들이 SNS를 통해 빨리 종량제 봉투를 사야 한다, 전쟁 때문에 이제 봉투를 못 산다고 해서 주변에 있는 마트나 편의점에 들러 어제... ",
			"pubDate":"Thu, 26 Mar 2026 15:02:00 +0900"
		},
		{
			"title":"[더벨][건설리포트] 서한, 자체사업 비중 확대에 수익성 개선",
			"originallink":"https:\/\/www.thebell.co.kr\/free\/content\/ArticleView.asp?key=202603241536198520104663",
			"link":"https:\/\/www.thebell.co.kr\/free\/content\/ArticleView.asp?key=202603241536198520104663",
			"description":"서한은 대구·경북뿐 아니라 인천 <b>청라<\/b>, 김포, 수원 호매실 등 수도권에도 다수의 토지를 확보하고 있다. 아직 구체적인 개발 계획은 확정되지 않았지만 자체사업과 매각을 병행하는 다양한 활용 방안을 검토 중이다.... ",
			"pubDate":"Thu, 26 Mar 2026 15:02:00 +0900"
		},
		{
			"title":"이마트 체험형 점포 전환 속도, 정용진 '스타필드 DNA'로 독립경영 스토...",
			"originallink":"https:\/\/www.businesspost.co.kr\/BP?command=article_view&num=434124",
			"link":"https:\/\/www.businesspost.co.kr\/BP?command=article_view&num=434124",
			"description":"사진은 정용진 회장(오른쪽에서 두 번째)이 23일 인천 스타필드<b>청라<\/b> 건설 현장을 방문한 모습. &lt;신세계그룹... 스타필드<b>청라<\/b> 등을 잇달아 방문하며 스타필드형 체험 공간들을 직접 챙기고 있다. 그룹 차원에서도 2025년... ",
			"pubDate":"Thu, 26 Mar 2026 14:44:00 +0900"
		},
		{
			"title":"암참 &quot;인천 <b>청라<\/b>하늘대교 통행료, 외국인도 통행료 감면 적용 필요&quot;",
			"originallink":"https:\/\/www.news1.kr\/industry\/company\/6115098",
			"link":"https:\/\/n.news.naver.com\/mnews\/article\/421\/0008851056?sid=101",
			"description":"인천 <b>청라<\/b>하늘대교 통행료와 관련, 글로벌 비즈니스 활성화와 글로벌 인재 유치 경쟁력을 고려할 때 외국인에게도 통행료 감면 혜택을 부여할 필요가 있다고 26일 밝혔다. 최근 개통한 <b>청라<\/b>하늘대교 통행료 지원은... ",
			"pubDate":"Thu, 26 Mar 2026 14:33:00 +0900"
		},
		{
			"title":"하나금융, 기부 캠페인 '해봄옷장' 진행…탄소중립·나눔문화 확산",
			"originallink":"http:\/\/www.newscape.co.kr\/news\/articleView.html?idxno=121220",
			"link":"http:\/\/www.newscape.co.kr\/news\/articleView.html?idxno=121220",
			"description":"참여는 하나은행 앱 'NEW 하나원큐'에서 신청할 수 있으며 명동·을지로·<b>청라<\/b> 등 주요 사옥에 설치된 기부함을 통해 직접 전달도 가능하다. 현장 방문이 어려운 참여자를 위해 무료 택배 서비스도 제공하고 기부 시... ",
			"pubDate":"Thu, 26 Mar 2026 14:22:00 +0900"
		},
		{
			"title":"[단독] &quot;전 회원 보상 단행&quot;...SSG 랜더스, '예매 시스템 오류' 공식 사과",
			"originallink":"https:\/\/www.youthdaily.co.kr\/news\/article.html?no=216243",
			"link":"https:\/\/www.youthdaily.co.kr\/news\/article.html?no=216243",
			"description":"이번 사태는 다가오는 '<b>청라<\/b>돔 시대'를 대비해 SSG닷컴과 협력하여 도입한 통합 예매 및 CRM 시스템 안착 과정에서 발생했다. 일상과 스포츠를 하나로 잇겠다는 비전 아래 추진된 신규 시스템이었으나, 접속자가 몰리며... ",
			"pubDate":"Thu, 26 Mar 2026 14:18:00 +0900"
		},
		{
			"title":"상암동 랜드마크 용지 '초고층의 저주' 풀린다",
			"originallink":"https:\/\/realty.chosun.com\/site\/data\/html_dir\/2026\/03\/26\/2026032602614.html",
			"link":"https:\/\/realty.chosun.com\/site\/data\/html_dir\/2026\/03\/26\/2026032602614.html",
			"description":"인천의 <b>청라<\/b>·송도도 초고층 랜드마크를 지으려고 하지만. 사업자를 찾지 못해 땅을 20년째 방치하고 있다. 서울시는 초고층을 포기하면서 기존 50%였던 지정 용도 비율을 40%로 낮추고, 국제컨벤션 설치 의무를... ",
			"pubDate":"Thu, 26 Mar 2026 14:16:00 +0900"
		},
		{
			"title":"SSG, 뿔난 팬들에 사과…티켓 예매 오류에 추가 보상",
			"originallink":"http:\/\/www.yonhapnewstv.co.kr\/AKR20260326141418Zie",
			"link":"https:\/\/m.sports.naver.com\/kbaseball\/article\/422\/0000848391",
			"description":"그러면서 &quot;구단은 다가올 <b>청라<\/b>돔 시대를 준비하며, 쓱닷컴(SSG.com)과 함께 시스템을 구축하는 과정에서... 저희 SSG랜더스는 다가올 <b>청라<\/b>돔 시대를 준비하며, SSG.COM과 함께 일상과 스포츠가 하나로 이어지는 시스템을... ",
			"pubDate":"Thu, 26 Mar 2026 14:15:00 +0900"
		},
		{
			"title":"인천 서구의회 정태완 의원 &quot;<b>청라<\/b> 커낼웨이 흡연 문제, 근본 대책 필요...",
			"originallink":"http:\/\/www.newstown.co.kr\/news\/articleView.html?idxno=698371",
			"link":"http:\/\/www.newstown.co.kr\/news\/articleView.html?idxno=698371",
			"description":"인천서구의회 정태완 의원 \/ 인천서구의회 인천 서구의회 정태완 의원이 <b>청라<\/b> 커낼웨이 일대 흡연 문제... 중인 <b>청라<\/b>호수공원·커낼웨이 환경개선사업과 연계한 대응을 제안했다. 특히 친수공간 및 야간경관 개선이... ",
			"pubDate":"Thu, 26 Mar 2026 14:13:00 +0900"
		},
		{
			"title":"투자엔 인색, 수익에만 진심…벤츠, 韓 EV 시장서 고전하는 이유",
			"originallink":"https:\/\/www.m-i.kr\/news\/articleView.html?idxno=1356671",
			"link":"https:\/\/www.m-i.kr\/news\/articleView.html?idxno=1356671",
			"description":"이 같은 변화의 배경으로는 벤츠코리아가 2024년 8월 인천 <b>청라<\/b>아파트 지하 주차장 전기차 화재 사건 이후... 특히 인천 <b>청라<\/b> 화재 이후 배터리 안전성과 정보 투명성에 대한 사회적 관심이 높아진 상황이어서, 정부와의... ",
			"pubDate":"Thu, 26 Mar 2026 14:12:00 +0900"
		},
		{
			"title":"[아유경제_부동산] 2026년 3월 4주 아파트 가격 동향… 매매가격 0.03% 상...",
			"originallink":"http:\/\/www.areyou.co.kr\/news\/articleView.html?idxno=93111",
			"link":"http:\/\/www.areyou.co.kr\/news\/articleView.html?idxno=93111",
			"description":"인천(0.11%)의 경우 연수구(0.21%)는 송도ㆍ동춘동 준신축 위주로, 서구(0.13%)는 마전ㆍ<b>청라<\/b>동 주요 단지 위주로, 중구(0.08%)는 운서ㆍ중산동 위주로, 미추홀구(0.07%)는 용현ㆍ관교동 중소형 규모 위주로, 남동구(0.07... ",
			"pubDate":"Thu, 26 Mar 2026 14:08:00 +0900"
		},
		{
			"title":"KB·신한·하나·우리등 4대 금융지주 주총 결산…주주환원 확대·내부통...",
			"originallink":"https:\/\/www.public25.com\/news\/articleView.html?idxno=42664",
			"link":"https:\/\/www.public25.com\/news\/articleView.html?idxno=42664",
			"description":"◆하나금융 주총, 올해부터 비과세 배당…9월 그룹 본사 <b>청라<\/b>로 이전 앞서  지난 24일 열린 하나금융지주... 이날 하나금융은 오는 9월 30일 그룹 본사를 인천 <b>청라<\/b>국제도시로 옮기는 내용의 정관 개정 안건도 의결했다.... ",
			"pubDate":"Thu, 26 Mar 2026 14:04:00 +0900"
		},
		{
			"title":"[<b>청라<\/b>언덕-서광호] 오늘은 죽지 마",
			"originallink":"https:\/\/www.imaeil.com\/page\/view\/2026032410592090767",
			"link":"https:\/\/n.news.naver.com\/mnews\/article\/088\/0001002831?sid=110",
			"description":"&quot;죽지 마.&quot; 이렇게 시작하는 래퍼 '매드클라운'의 음악, 제목도 '죽지 마'이다. 이 음악을 들으며 가사를 곱씹는다. &quot;완벽하게 안 살아도 돼… 한 시간만 더 살아보자… 한 달만 더 살아보자… 지나가면 진짜 아무것도 아냐... ",
			"pubDate":"Thu, 26 Mar 2026 14:04:00 +0900"
		},
		{
			"title":"이마트 한채양 &quot;대형점 6곳 몰로 전환… 성장기반 강화&quot;",
			"originallink":"https:\/\/it.chosun.com\/news\/articleView.html?idxno=2023092159283",
			"link":"https:\/\/it.chosun.com\/news\/articleView.html?idxno=2023092159283",
			"description":"일부 주주들은 스타필드 <b>청라<\/b> 개발과 동서울터미널 부지, AI 데이터센터 투자 등을 언급하며 재무 부담 가능성을 지적했다. 이에 대해 한 대표는 &quot;현금만을 지키는 전략으로는 회사의 미래를 담보할 수 없다&quot;며 &quot;새로운... ",
			"pubDate":"Thu, 26 Mar 2026 13:10:00 +0900"
		},
		{
			"title":"[인천TV] 세계 최고 높이 184m <b>청라<\/b>하늘대교 전망대 4월말 개장",
			"originallink":"https:\/\/www.incheontoday.com\/news\/articleView.html?idxno=316963",
			"link":"https:\/\/www.incheontoday.com\/news\/articleView.html?idxno=316963",
			"description":"인천투데이=홍지은 PD | 유정복 인천시장이 4월 말 개장을 앞둔 <b>청라<\/b>하늘대교 관광시설을 직접 찾아 막바지... 인천시는 유 시장이 25일 오후 <b>청라<\/b>하늘대교 관광시설 현장을 찾아 시설 운영 계획과 안전 대책 등 개장... ",
			"pubDate":"Thu, 26 Mar 2026 12:54:00 +0900"
		},
		{
			"title":"이용우 의원 &quot;하나금융그룹 '<b>청라<\/b> 시대' 환영…행정적ㆍ정책적 지원&quot;",
			"originallink":"http:\/\/www.lawleader.co.kr\/news\/articleView.html?idxno=18812",
			"link":"http:\/\/www.lawleader.co.kr\/news\/articleView.html?idxno=18812",
			"description":"이용우 더불어민주당 국회의원이 &quot;하나금융그룹의 '<b>청라<\/b> 시대' 공식화를 환영한다&quot;며 &quot;하나금융그룹이 <b>청라<\/b>에 안정적으로 뿌리내려, 세계가 주목하는 금융 중심지로 <b>청라<\/b>국제도시가 우뚝 설 수 있을 때까지 모든... ",
			"pubDate":"Thu, 26 Mar 2026 12:38:00 +0900"
		},
		{
			"title":"[건강올레길] 따뜻한 봄바람과 함께 찾아오는 불청객 ‘스트레스성 위장...",
			"originallink":"https:\/\/sports.donga.com\/life\/article\/all\/20260326\/133604606\/1",
			"link":"https:\/\/n.news.naver.com\/mnews\/article\/382\/0001264369?sid=103",
			"description":"겨우내 움츠러들었던 몸을 깨우는 봄, 위장 건강 상태를 꼼꼼히 점검하고 체계적인 검진 계획을 세우는 게 건강한 한 해를 보내는 첫걸음이다. 인천 <b>청라<\/b> 다정한내과 최현석 원장(내과 전문의)",
			"pubDate":"Thu, 26 Mar 2026 11:45:00 +0900"
		},
		{
			"title":"이마트, 올해 6개점 몰 타입 전환ㆍ연말 트레이더스 1개점 출점",
			"originallink":"https:\/\/www.dnews.co.kr\/uhtml\/view.jsp?idxno=202603261136080740765",
			"link":"https:\/\/www.dnews.co.kr\/uhtml\/view.jsp?idxno=202603261136080740765",
			"description":"정 회장이 올해 들어 찾은 현장은 △스타필드마켓 죽전 △스타필드빌리지 운정 △AI 데이터센터 MOU △스타필드 <b>청라<\/b> 등 4곳으로, 모두 기존 대형마트 포맷이 아닌 새로운 비즈니스 모델이다. 올해는 이들 신규 포맷의... ",
			"pubDate":"Thu, 26 Mar 2026 11:40:00 +0900"
		}
	]
}