{
	"lastBuildDate":"Tue, 07 Jan 2025 16:20:02 +0900",
	"total":254831,
	"start":1,
	"display":30,
	"items":[
		{
			"title":"너도나도 &quot;SUV 탈래&quot; … 국민 세단 제친 쏘렌토, 첫 판매 1위",
			"originallink":"https:\/\/www.mk.co.kr\/article\/11211935",
			"link":"https:\/\/n.news.naver.com\/mnews\/article\/009\/0005425163?sid=103",
			"description":"전기차 캐즘에 더해 <b>청라<\/b> 전기차 화재가 소비에 하방 압력으로 작용했으나 여전히 테슬라는 견고했다. 판매량 2위와 3위는 국내 수입차 시장의 전통 강자인 BMW와 메르세데스 벤츠의 준대형 세단이 나눠... ",
			"pubDate":"Tue, 07 Jan 2025 16:04:00 +0900"
		},
		{
			"title":"벤츠의 전기차 위기, 'BMW 1위 굳히기' 기회로",
			"originallink":"https:\/\/www.dailian.co.kr\/news\/view\/1449042\/?sc=Naver",
			"link":"https:\/\/n.news.naver.com\/mnews\/article\/119\/0002911444?sid=101",
			"description":"지난해 8월 발생한 인천 <b>청라<\/b> 지하주차장 전기차 화재 사건이 메르세데스-벤츠의 전기차 판매량 급감과... 앞서 지난해 8월1일 인천 서구 <b>청라<\/b>국제도시의 한 아파트 지하주차장에 주차된 전기차에서 불이 나면서... ",
			"pubDate":"Tue, 07 Jan 2025 15:15:00 +0900"
		},
		{
			"title":"충북 아파트 지하주차장 19곳 스프링클러 시설 불량 적발",
			"originallink":"https:\/\/www.news1.kr\/local\/sejong-chungbuk\/5653690",
			"link":"https:\/\/n.news.naver.com\/mnews\/article\/421\/0008008402?sid=102",
			"description":"이번 조사는 지난해 8월 인천 <b>청라<\/b>의 아파트에서 일어난 지하주차장 전기차 화재에 따라 소방당국이 조사한 것이다. 긴급화재안전조사는 사전 고지 없이 불시 조사 원칙이다. 소방당국은 소방시설 정지와 피난... ",
			"pubDate":"Tue, 07 Jan 2025 14:38:00 +0900"
		},
		{
			"title":"2년 연속 수입차 판매 1위 BMW…비결 살펴보니",
			"originallink":"https:\/\/www.asiatime.co.kr\/article\/20250107500271",
			"link":"https:\/\/www.asiatime.co.kr\/article\/20250107500271",
			"description":"전기차 충전 인프라 확충하고 인천 <b>청라<\/b>에 한국 시장만을 위한 새로운 연구개발(R&amp;D)센터를 설립하는 등 투자도 늘렸다. 고객이 차량을 직접 체험해 볼 수 있는 드라이빙센터도 효과를 봤다. 2014년 인천국제공항... ",
			"pubDate":"Tue, 07 Jan 2025 14:36:00 +0900"
		},
		{
			"title":"박일하 동작구청장, 공동주택 열화상 카메라 현장 시연회 참여",
			"originallink":"http:\/\/www.aptn.co.kr\/news\/articleView.html?idxno=108296",
			"link":"http:\/\/www.aptn.co.kr\/news\/articleView.html?idxno=108296",
			"description":"지난해 8월 인천 <b>청라<\/b> 아파트 화재 이후 열화상 카메라의 필요성이 대두되기도 했다. 이에 동작구는 지난해 11월 21일 보안·감시장비 전문 업체 세이프티 월드와 '공동주택 전기차 화재 예방을 위한 열화상 카메라 관제... ",
			"pubDate":"Tue, 07 Jan 2025 13:44:00 +0900"
		},
		{
			"title":"인천 계양 산업 단지 2차 분양 세부 일정 조정중",
			"originallink":"https:\/\/www.hellot.net\/news\/article.html?no=96911",
			"link":"https:\/\/www.hellot.net\/news\/article.html?no=96911",
			"description":"또한, 수도권 제1 순환 고속도로(계양 IC), 경명대로(인천 <b>청라<\/b>-경기 부천), 국도 39호선이 연결되어 있어... (인천 <b>청라<\/b>-경기 부천), 국도 39호선 연결된다. 특히 계양산업단지 진출입 도로인 북측 경명대로는 수도권... ",
			"pubDate":"Tue, 07 Jan 2025 13:22:00 +0900"
		},
		{
			"title":"전기차 충전업계의 생존게임…캐즘의 늪에서 활로를 찾아라",
			"originallink":"https:\/\/www.electimes.com\/news\/articleView.html?idxno=348775",
			"link":"https:\/\/www.electimes.com\/news\/articleView.html?idxno=348775",
			"description":"이른바 '캐즘(Chasm, 일시적 수요 정체)'에 진입한 전기차 시장의 성장세 둔화와 지난해 8월 인천 <b>청라<\/b> 화재... 이러한 시장 침체 속에서 지난해 8월 인천 <b>청라<\/b> 아파트단지에서 발생한 대규모 전기차 화재는 캐즘 극복을... ",
			"pubDate":"Tue, 07 Jan 2025 13:16:00 +0900"
		},
		{
			"title":"인천환경공단, 소각재 재활용 용역 특정업체 몰아줘 '지적' 나와",
			"originallink":"http:\/\/www.incheontoday.com\/news\/articleView.html?idxno=260314",
			"link":"http:\/\/www.incheontoday.com\/news\/articleView.html?idxno=260314",
			"description":"인천 서구 소재 <b>청라<\/b>자원환경센터(<b>청라<\/b>소각장)의 모습.(사진제공 인천시) 인천환경공단, 2023년에도 <b>청라<\/b>소각장 수상한 입찰 인천환경공단은 지난 2023년에도 <b>청라<\/b>소각장 바닥재 처리 용역 입찰 과정에서도 문제가... ",
			"pubDate":"Tue, 07 Jan 2025 11:56:00 +0900"
		},
		{
			"title":"[1월 7일 오늘의 PIck] 검단구 신설 코앞인데… 북부순환망 구축 '지연'...",
			"originallink":"http:\/\/ch1.skbroadband.com\/content\/view?parent_no=24&content_no=58&p_no=176861",
			"link":"http:\/\/ch1.skbroadband.com\/content\/view?parent_no=24&content_no=58&p_no=176861",
			"description":"늘어나는 <b>청라<\/b> 상가 공실률… 시행사, 관리 대신 회피 한국부동산원 부동산 통계 정보를 보면 지난 2023년도 1분기에 3.93%였던 <b>청라<\/b>국제도시 집합 상가 공실률은 지난해 3분기 5.02%로 훌쩍 뛰었습니다. 미분양된 공실... ",
			"pubDate":"Tue, 07 Jan 2025 11:36:00 +0900"
		},
		{
			"title":"서울아산은 <b>청라<\/b>·서울대는 배곧… 분원 건립 첫 삽 뜨나",
			"originallink":"https:\/\/biz.chosun.com\/science-chosun\/medicine-health\/2025\/01\/07\/DP2SXJNYUVGTTODE5XZMQ4YZGM\/?utm_source=naver&utm_medium=original&utm_campaign=biz",
			"link":"https:\/\/n.news.naver.com\/mnews\/article\/366\/0001045408?sid=105",
			"description":"6일 의료계에 따르면, 올해 서울대병원과 서울아산병원이 각각 시흥 배곧과 인천 <b>청라<\/b>에 병원 설립 공사... 인천 <b>청라<\/b>의료복합타운에 짓는 서울아산병원<b>청라<\/b> 건립 공사도 올해 착공될 전망이다.... ",
			"pubDate":"Tue, 07 Jan 2025 06:01:00 +0900"
		},
		{
			"title":"4000억 vs 2000억 원... 국토부·인천시, 제3연륙교 손실 보전 놓고 '충돌...",
			"originallink":"https:\/\/www.hankookilbo.com\/News\/Read\/A2025010216250003066?did=NA",
			"link":"https:\/\/n.news.naver.com\/mnews\/article\/469\/0000842681?sid=102",
			"description":"이는 2006년 한국토지주택공사(LH)가 영종·<b>청라<\/b> 택지 조성 원가에 5,000억 원을 반영해 사업비를 확보했는데도 제3연륙교 건설이 10년 넘게 지연된 이유다. 인천 중구 중산동부터 서구 <b>청라<\/b>동까지 총길이 4.6㎞(해상 교량... ",
			"pubDate":"Tue, 07 Jan 2025 05:00:00 +0900"
		},
		{
			"title":"'판교~광화문 15분' UAM, 생닭 쏴서 충격 시험?…조류 충돌 대책 없다",
			"originallink":"http:\/\/news.mt.co.kr\/mtview.php?no=2025010614270695856",
			"link":"https:\/\/n.news.naver.com\/mnews\/article\/008\/0005137676?sid=101",
			"description":"<b>청라<\/b>·굴포천하구, 한강하구, 한강하류, 탄천 등 철새도래지 4곳이 수도권 UAM 노선으로 유력시되는 것을 감안하면 조류 충돌은 물론 빌딩풍 등 정밀 안전 대책이 뒷받침되어야 한다는 지적이 나온다. UAM 업계 관계자는... ",
			"pubDate":"Tue, 07 Jan 2025 04:40:00 +0900"
		},
		{
			"title":"&quot;전기차 안전성 불신, 균형잡힌 정보전달로 극복해야&quot;",
			"originallink":"https:\/\/www.electimes.com\/news\/articleView.html?idxno=348816",
			"link":"https:\/\/www.electimes.com\/news\/articleView.html?idxno=348816",
			"description":"이어 &quot;<b>청라<\/b> 아파트 지하주차장 화재의 경우 확산의 주원인이 스프링클러 미작동이었으나, 이러한 정보는 제대로 전달되지 않았다&quot;고 덧붙였다. 박용희 소프트베리 대표는 &quot;전기차 관련 정보의 양극화 현상이 심화되고 있다... ",
			"pubDate":"Tue, 07 Jan 2025 03:16:00 +0900"
		},
		{
			"title":"[인천판\/게시판]인천 外",
			"originallink":"https:\/\/www.donga.com\/news\/Society\/article\/all\/20250106\/130801524\/2",
			"link":"https:\/\/n.news.naver.com\/mnews\/article\/020\/0003608436?sid=102",
			"description":"13∼15일 오전 10시∼11시 반 <b>청라<\/b>호수도서관 회의실. □독서 교실=초등학교 1∼3학년 대상 ‘2025년 겨울 독서교실―하늘의 실험왕’ 참가자 20명. 13∼16일 오전 10시∼낮 12시 반 영종하늘도서관 세미나실1.... ",
			"pubDate":"Tue, 07 Jan 2025 03:07:00 +0900"
		},
		{
			"title":"17년 표류 ‘인천 로봇랜드’ 3월 첫 삽 뜬다",
			"originallink":"https:\/\/www.donga.com\/news\/Society\/article\/all\/20250106\/130801542\/2",
			"link":"https:\/\/n.news.naver.com\/mnews\/article\/020\/0003608434?sid=102",
			"description":"현재 서구 <b>청라<\/b>동 인천 로봇랜드 사업 부지에는 2017년 국·시비 1100억 원을 들여 세운 지상 23층짜리 로봇... 특히 올해 말 개통 예정인 제3연륙교(영종∼<b>청라<\/b>) 인근에 인천 로봇랜드가 위치하고 있어 관련 기업 유치에... ",
			"pubDate":"Tue, 07 Jan 2025 03:07:00 +0900"
		},
		{
			"title":"2025년은 푸른 뱀의 해…뱀띠 건설인 누가 있나",
			"originallink":"https:\/\/news.tf.co.kr\/read\/economy\/2167741.htm",
			"link":"https:\/\/n.news.naver.com\/mnews\/article\/629\/0000354176?sid=101",
			"description":"용산철도병원부지, 잠실 스포츠마이스(MICE), <b>청라<\/b> 의료복합타운, 공릉역세권개발사업 등이 대표적이다. 굵직한 사업을 앞둔 HDC현대산업개발을 정 대표가 어떻게 이끌어갈지 주목된다. 남궁홍 삼성E&amp;A 대표도... ",
			"pubDate":"Tue, 07 Jan 2025 00:00:00 +0900"
		},
		{
			"title":"늘어나는 <b>청라<\/b> 상가 공실률… 시행사, 관리 대신 회피",
			"originallink":"https:\/\/www.kyeongin.com\/article\/1725246?ref=naver",
			"link":"https:\/\/www.kyeongin.com\/article\/1725246?ref=naver",
			"description":"인천 <b>청라<\/b>국제도시의 한 대형 상가가 텅 비어있다. 이 상가를 관리하는 시행사가 공과금 수억원을 미납해 현재 입주한 업체들마저도 피해를 입고 있는 실정이다. 2025.1.6 \/조재현기자 jhc@kyeongin.com 인천 <b>청라<\/b>국제도시에서... ",
			"pubDate":"Mon, 06 Jan 2025 20:14:00 +0900"
		},
		{
			"title":"인천시, 역대 최대 국비 6.9조 달성 … 보통교부세 1조 원 시대 열어",
			"originallink":"https:\/\/www.kmaeil.com\/news\/articleView.html?idxno=487522",
			"link":"https:\/\/www.kmaeil.com\/news\/articleView.html?idxno=487522",
			"description":"이번 국비 확보에는 ▲수도권광역급행철도(GTX-B) 3,630억 원 ▲서울도시철도 7호선 <b>청라<\/b> 연장 793억 원 ▲인천발 KTX 350억 원 ▲스마트빌리지 보급 및 확산 232억 원 ▲노인 일자리 지원 1,204억 원 등이 포함됐다. 이들... ",
			"pubDate":"Mon, 06 Jan 2025 20:12:00 +0900"
		},
		{
			"title":"인천 북부순환망 구축 지연",
			"originallink":"https:\/\/www.incheonilbo.com\/news\/articleView.html?idxno=1275781",
			"link":"https:\/\/www.incheonilbo.com\/news\/articleView.html?idxno=1275781",
			"description":"시는 서울 7호선 <b>청라<\/b>연장선을 인천2호선 왕길역과 이어 북부순환망 서쪽 연결망을 만드는 노선은 B\/C값이 0.34로 경제성 낮고, 장기적으로 검단-김포의 도시 활성화 이후 추진이 가능할 것으로 판단했다. 7호선과 함께... ",
			"pubDate":"Mon, 06 Jan 2025 19:56:00 +0900"
		},
		{
			"title":"&quot;전기차 못 믿어&quot; 불신 커지자 일어난 일…하이브리드차, 가솔린 제쳤다",
			"originallink":"https:\/\/www.sedaily.com\/NewsView\/2GNL7UVTMX",
			"link":"https:\/\/n.news.naver.com\/mnews\/article\/011\/0004436488?sid=101",
			"description":"벤츠는 지난해 8월 발생한 인천 <b>청라<\/b>국제도시 아파트 지하주차장 화재 사고 당시 원인이었던 벤츠 전기차의 중국산 배터리 사용 사실이 드러나며 브랜드 이미지에 타격을 입었다는 평가를 받았다.... ",
			"pubDate":"Mon, 06 Jan 2025 18:15:00 +0900"
		},
		{
			"title":"기차 타고 땅끝마을로... 다시 만난 낭만열차도 반갑다 [박장식의 환승...",
			"originallink":"https:\/\/www.ohmynews.com\/NWS_Web\/View\/at_pg.aspx?CNTN_CD=A0003093719&CMPT_CD=P0010&utm_source=naver&utm_medium=newsearch&utm_campaign=naver_news",
			"link":"https:\/\/n.news.naver.com\/mnews\/article\/047\/0002458735?sid=101",
			"description":"<b>청라<\/b>국제도시와 영종하늘도시를 잇는 제3연륙교(가칭)가 오는 12월 개통될 예정이다. 제3연륙교는 고속도로... 특히 영종하늘도시와 <b>청라<\/b>국제도시 주민의 경우 무료로 통행할 수 있고, 지역 주민이 아니더라도 자전거와... ",
			"pubDate":"Mon, 06 Jan 2025 17:48:00 +0900"
		},
		{
			"title":"[인천TV] 인천 국비 6조8700억원 확보...GTX-B·서울7호선 <b>청라<\/b>연장 등",
			"originallink":"http:\/\/www.incheontoday.com\/news\/articleView.html?idxno=260285",
			"link":"http:\/\/www.incheontoday.com\/news\/articleView.html?idxno=260285",
			"description":"이번 국비에는 GTX-B 3630억원, 서울도시철도 7호선 <b>청라<\/b>연장 793억원, 인천발 KTX 350억원, 스마트빌리지 보급·확산 232억원, 노인 일자리 지원 1204억원 등이 반영됐습니다. 유정복 시장은 &quot;3년 연속 국비 6조원 확보는... ",
			"pubDate":"Mon, 06 Jan 2025 17:38:00 +0900"
		},
		{
			"title":"[2025신년사] 인천 중구의회 이종호 의장 &quot;분구 앞두고 유종의 미 위해 ...",
			"originallink":"https:\/\/www.newscj.com\/news\/articleView.html?idxno=3219587",
			"link":"https:\/\/www.newscj.com\/news\/articleView.html?idxno=3219587",
			"description":"또한 제물포구 기초의원 정수 확대 건의문, 영종-<b>청라<\/b> 제3연륙교 체험·관광시설 축소 철회 촉구 성명서, 제물포구 신청사 부지 변경 전면 재검토 촉구 결의문, 제3연륙교 명칭 영종하늘대교 선정 촉구 결의문 등 중구... ",
			"pubDate":"Mon, 06 Jan 2025 17:28:00 +0900"
		},
		{
			"title":"글로벌 은행, 재생에너지 전력구매 확대, 국내 은행은?",
			"originallink":"https:\/\/www.ekoreanews.co.kr\/news\/articleView.html?idxno=77239",
			"link":"https:\/\/www.ekoreanews.co.kr\/news\/articleView.html?idxno=77239",
			"description":"하나금융은 <b>청라<\/b> 데이터센터 등에 태양광·지열 발전을 운영 중이며, KB금융은 37개소에 태양광 발전설비를 구축해놓은 상태다. 미래에셋증권은 국내 금융사 중 유일하게 태양광 발전사와 PPA(전력구매계약)로 변경할... ",
			"pubDate":"Mon, 06 Jan 2025 17:24:00 +0900"
		},
		{
			"title":"'e편한세상 동인천 베이프런트' 선착순 계약 소식에 주택전시관 '인산인...",
			"originallink":"https:\/\/www.gpkorea.com\/news\/articleView.html?idxno=123600",
			"link":"https:\/\/www.gpkorea.com\/news\/articleView.html?idxno=123600",
			"description":"올해 사전타당성용역을 실시할 계획인 이 신설 철도는 송도달빛축제공원역에서 국제여객터미널역, e편한세상 동인천 베이프런트 인근에 위치한 신포역, 동인천역, <b>청라<\/b>국제업무지구역, <b>청라<\/b>국제도시역, 왕길역을 거쳐... ",
			"pubDate":"Mon, 06 Jan 2025 17:18:00 +0900"
		},
		{
			"title":"“70~80년대 만화영화를 그대로 재현”, 김중환 작가 피규어 전시회 11일...",
			"originallink":"https:\/\/game.donga.com\/115418\/",
			"link":"https:\/\/game.donga.com\/115418\/",
			"description":"국내 탑 모델러 중 하나로 손꼽히는 OVW(김중환)작가가 오는 2025년 1월 11일 토요일 12:00 ~ 19:00까지 인천에 소재한 <b>청라<\/b> 블루노바홀에서 피규어 전시회를 개최한다. 이번에 준비되는 피규어 전시회는 멀리는 60년대부터... ",
			"pubDate":"Mon, 06 Jan 2025 16:46:00 +0900"
		},
		{
			"title":"상황따라 변하는 인천환경공단 입찰 적격심사…3년전 입찰 재조명",
			"originallink":"http:\/\/www.kihoilbo.co.kr\/news\/articleView.html?idxno=1126927",
			"link":"http:\/\/www.kihoilbo.co.kr\/news\/articleView.html?idxno=1126927",
			"description":"공단은 최근 송도와 <b>청라<\/b>사업소의 소각재·바닥재 폐기물 처리용역 입찰 참가 자격에 허가 등급을 설정해... 6일 재활용 업계 등에 따르면 공단은 지난 2022년 12월 <b>청라<\/b>사업소 소각재 처리용역 입찰 공고문을 조달청... ",
			"pubDate":"Mon, 06 Jan 2025 16:34:00 +0900"
		},
		{
			"title":"인천시, 올해 국비 6조8,729억 확보…역대 최고치",
			"originallink":"http:\/\/news.lghellovision.net\/news\/articleView.html?idxno=492874",
			"link":"http:\/\/news.lghellovision.net\/news\/articleView.html?idxno=492874",
			"description":"주요 국비 확보 사업은 수도권광역급행철도 GTX-B가 3천630억 원, 서울도시철도 7호선 <b>청라<\/b> 연장 793억 원, 인천발 KTX 350억 원, 스마트빌리지 보급 및 확산 232억 원, 노인 일자리 지원 1천204억 원 등입니다.",
			"pubDate":"Mon, 06 Jan 2025 15:32:00 +0900"
		},
		{
			"title":"인천시, 역대 최대 국비 6.9조 달성 … 보통교부세 1조 시대 열어",
			"originallink":"http:\/\/www.incheonnews.com\/news\/articleView.html?idxno=422931",
			"link":"http:\/\/www.incheonnews.com\/news\/articleView.html?idxno=422931",
			"description":"인천시 자료 이번 국비 확보에는 ▲수도권광역급행철도(GTX-B) 3,630억 원 ▲서울도시철도 7호선 <b>청라<\/b> 연장 793억 원 ▲인천발 KTX 350억 원 ▲스마트빌리지 보급 및 확산 232억 원 ▲노인 일자리 지원 1,204억 원 등이... ",
			"pubDate":"Mon, 06 Jan 2025 15:32:00 +0900"
		},
		{
			"title":"옛날통닭 프랜차이즈 두레통닭, <b>청라<\/b>·진주·포항·거제 등 신규 오픈",
			"originallink":"http:\/\/www.kbsm.net\/news\/view.php?idx=460020",
			"link":"http:\/\/www.kbsm.net\/news\/view.php?idx=460020",
			"description":"최근 <b>청라<\/b>, 진주, 포항, 거제 등 지역에 가맹점을 신규 오픈했다. 최근 불경기로 인해 자영업자들이 어려움을... 인천<b>청라<\/b>1호점, 진주상대하대점, 포항구룡포점, 양주광백점, 수원권선점 등을 신규 오픈했다. 두레통닭은... ",
			"pubDate":"Mon, 06 Jan 2025 13:56:00 +0900"
		}
	]
}