{
	"lastBuildDate":"Mon, 08 Sep 2025 07:50:01 +0900",
	"total":273184,
	"start":1,
	"display":30,
	"items":[
		{
			"title":"인천시 서구 새 이름은 '서해구'...내년 7월 출범",
			"originallink":"https:\/\/www.ytn.co.kr\/_ln\/0115_202509080252164326",
			"link":"https:\/\/n.news.naver.com\/mnews\/article\/052\/0002243832?sid=102",
			"description":"[강범석 \/ 인천 서구청장 (지난달 21일) : 단계에 걸쳐서 최초 4개의 안 중에서 2개로 줄이고 그 2개인 <b>청라<\/b>구와 서해구 중에 주민 여론조사를 통해서 최종적으로 서해구로….] 서구는 미래 비전 소위원회를 구성해 도시... ",
			"pubDate":"Mon, 08 Sep 2025 02:52:00 +0900"
		},
		{
			"title":"신성영 의원 ‘제3연륙교 무료화 환영’과 국가 책임감 촉구 질의",
			"originallink":"https:\/\/m.skyedaily.com\/news_view.html?ID=284443",
			"link":"https:\/\/m.skyedaily.com\/news_view.html?ID=284443",
			"description":"영종과 <b>청라<\/b> 주민에게 횟수 제한 없는 무료 통행을 보장하고 나아가 인천시민 전체로 혜택을 확대한 점을 높이 평가한다”고 말했다. 그러나 “국토교통부가 국제형사재판소 판결을 근거로 1조 원이 넘는 손실보전금을... ",
			"pubDate":"Sun, 07 Sep 2025 23:46:00 +0900"
		},
		{
			"title":"[SW인터뷰] 천하의 김광현도 울컥했다 “2000K, 신인 땐 상상도 못했다”",
			"originallink":"https:\/\/www.sportsworldi.com\/newsView\/20250907511249",
			"link":"https:\/\/m.sports.naver.com\/kbaseball\/article\/396\/0000720589",
			"description":"2028년부터 <b>청라<\/b>돔 시대가 열리는 상황. 그 전에 200승을 채우겠다는 다짐이다. 김광현은 “개인적으로 200승이 최종목표라고 생각한다”며 “2000탈삼진이 개인적이 기록이라면, 200승은 팀 승리와도 연관되지 않나.... ",
			"pubDate":"Sun, 07 Sep 2025 23:02:00 +0900"
		},
		{
			"title":"‘구월 상권’ 두고… 신세계-롯데 ‘2차 대전’",
			"originallink":"https:\/\/www.kyeongin.com\/article\/1751007",
			"link":"https:\/\/www.kyeongin.com\/article\/1751007",
			"description":"신세계와 롯데는 송도·<b>청라<\/b>국제도시에도 대형 유통시설 건립을 추진하고 있어 인천 전역에서 이들 유통... 신세계는 <b>청라<\/b>국제도시에 돔구장이 들어서는 스타필드 <b>청라<\/b> 건립 공사를 진행하고 있으며 롯데도... ",
			"pubDate":"Sun, 07 Sep 2025 20:04:00 +0900"
		},
		{
			"title":"[인천 MOU 잔혹사] '세계 성장 잠재력 2위'인데… 투자 실패 왜 반복되나",
			"originallink":"https:\/\/www.joongboo.com\/news\/articleView.html?idxno=363702715",
			"link":"https:\/\/www.joongboo.com\/news\/articleView.html?idxno=363702715",
			"description":"이외에도 2015년 홍콩기업 CTF그룹과 맺은 영종복합리조트 조성 MOU, 2017년 '강화남단휴먼메디시티' 개발을 위해 파나핀토글로벌파트너스와 체결한 MOU, 2023년 체결된 '<b>청라<\/b> 지테크시티(G-Tech city)' 조성 MOU도 모두... ",
			"pubDate":"Sun, 07 Sep 2025 16:30:00 +0900"
		},
		{
			"title":"&quot;수도권매립지 제4매립장, '국가정원' 지정 추진해야&quot;",
			"originallink":"https:\/\/www.joongboo.com\/news\/articleView.html?idxno=363702704",
			"link":"https:\/\/www.joongboo.com\/news\/articleView.html?idxno=363702704",
			"description":"스타필드 <b>청라<\/b> 등의 시설과 시너지도 기대된다&quot;고 답변했다. 그러면서 유 시장은 &quot;인천시가 환경부, 서울시, 경기도와 사용 종료를 추진 중인 수도권매립지가 '보물단지'로 거듭날 수 있도록 노력하겠다&quot;며 &quot;국가정원... ",
			"pubDate":"Sun, 07 Sep 2025 16:02:00 +0900"
		},
		{
			"title":"이규생 인천시체육회 회장 “남은 임기, 공약 완수에 총력” [경기인터...",
			"originallink":"https:\/\/www.kyeonggi.com\/article\/20250907580063",
			"link":"https:\/\/m.sports.naver.com\/general\/article\/666\/0000082829",
			"description":"<b>청라<\/b>에 새 홈구장 계획이 가시화되면서 문학권역 활용 방안을 선제적으로 준비해야 한다. 시민 스포츠·청소년·생활체육의 거점, e스포츠·페스티벌 등 복합 스포츠·문화 공간으로 포스트-프로야구 시대의 활용 로드맵을... ",
			"pubDate":"Sun, 07 Sep 2025 15:59:00 +0900"
		},
		{
			"title":"&quot;복층이라더니 다락&quot;… <b>청라<\/b> A오피스텔 법정에 올라, 과장된 광고 막을...",
			"originallink":"http:\/\/www.incheonnews.com\/news\/articleView.html?idxno=428989",
			"link":"http:\/\/www.incheonnews.com\/news\/articleView.html?idxno=428989",
			"description":"<b>청라<\/b>국제도시 A오피스텔 전경. 제보자 포토 인천뉴스 박창우 기자ㅣ인천 <b>청라<\/b>국제도시역 인근에서 분양된 A오피스텔이 '복층'이라 홍보됐지만, 실제로는 사람이 앉기조차 힘든 '다락'에 불과하다는 사실이 드러나면서... ",
			"pubDate":"Sun, 07 Sep 2025 15:38:00 +0900"
		},
		{
			"title":"[사설] 인천대교 손실 '돌려막기' 영종대교 통행료 연장 징수 안돼",
			"originallink":"https:\/\/www.incheontoday.com\/news\/articleView.html?idxno=307896",
			"link":"https:\/\/www.incheontoday.com\/news\/articleView.html?idxno=307896",
			"description":"영종대교와 제3연륙교는 모두 영종과 <b>청라<\/b>를 이어 통행권역이 같은 경쟁 노선이라 할 수 있다. 통행료에... 제3연륙교는 영종·<b>청라<\/b> 개발 당시 한국토지주택공사(LH)가 분양가에 건설비를 반영해 재원을 마련했는데... ",
			"pubDate":"Sun, 07 Sep 2025 15:06:00 +0900"
		},
		{
			"title":"유정복 인천시장 ‘민생 최전선 행정’ 희망을 쏘다",
			"originallink":"https:\/\/m.skyedaily.com\/news_view.html?ID=284429",
			"link":"https:\/\/m.skyedaily.com\/news_view.html?ID=284429",
			"description":"제3연륙교 통행료 무료화는 단순한 요금 문제가 아니라 영종·<b>청라<\/b> 주민의 삶과 직결된 민생 현안이다. 여기에 원도심 재생과 균형발전 정책을 결합해 도시 전체가 골고루 성장하는 인천을 하얀 도화지 위에 그려냈다.... ",
			"pubDate":"Sun, 07 Sep 2025 10:08:00 +0900"
		},
		{
			"title":"인천시 서구 <b>청라<\/b>1동, ‘친환경 화장품 만들기’ 체험 추진",
			"originallink":"https:\/\/www.siminilbo.co.kr\/news\/newsview.php?ncode=1160291443530603",
			"link":"https:\/\/www.siminilbo.co.kr\/news\/newsview.php?ncode=1160291443530603",
			"description":"인천 서구 <b>청라<\/b>1동 행정복지센터(동장 김난영)는 주민자치회(회장 최한수)가 지난달 29일, ‘친환경 화장품... 최한수 <b>청라<\/b>1동 주민자치회장은 “세계적으로 우리나라 화장품의 인기가 높아져, 미용과 환경을 결합한... ",
			"pubDate":"Sun, 07 Sep 2025 10:00:00 +0900"
		},
		{
			"title":"'그릭 요거트' 인기↑…풀무원다논, 쿠킹 클래스 통해 활용법 제안",
			"originallink":"https:\/\/www.thepublic.kr\/news\/articleView.html?idxno=275634",
			"link":"https:\/\/www.thepublic.kr\/news\/articleView.html?idxno=275634",
			"description":"풀무원요거트 그릭과 함께하는 가을학기 쿠킹 클래스는 <b>청라<\/b>점을 시작으로 오는 11월 1일까지 약 3개월간 전국 롯데마트 문화센터 지점에서 진행된다. 자세한 일정과 수강신청 방법, 실리팟 협업 클래스 여부는... ",
			"pubDate":"Sun, 07 Sep 2025 08:58:00 +0900"
		},
		{
			"title":"'3년 18억' 재계약, 그런데 눈치 보고 다녔다?…&quot;나 때문에 안 좋으면 어...",
			"originallink":"https:\/\/www.xportsnews.com\/article\/2050185",
			"link":"https:\/\/m.sports.naver.com\/kbaseball\/article\/311\/0001914242",
			"description":"또한 SSG 관계자는 &quot;최대 3년 계약은 <b>청라<\/b>돔 시대를 염두해 뒀다. 3년 기간 설정에는 리모델링 중간 성과와 <b>청라<\/b>돔 시대를 위한 단계적 목표, 감독 재계약 사례 등을 종합적으로 검토해 결정했다&quot;며 &quot;감독 재계약... ",
			"pubDate":"Sun, 07 Sep 2025 08:46:00 +0900"
		},
		{
			"title":"인천 서구, ‘서해구’ 명칭 변경·제3연륙교 이름 두고 갈등 심화",
			"originallink":"https:\/\/www.news1.kr\/local\/incheon\/5903115",
			"link":"https:\/\/n.news.naver.com\/mnews\/article\/421\/0008470517?sid=102",
			"description":"서구는 <b>청라<\/b>와 영종도를 잇는 제3연륙교 명칭을 두고도 중구 주민들과 대립 중이다. 앞서 인천시 지명위원회는 다리 이름을 ‘<b>청라<\/b>하늘대교’로 확정했지만, 중구 주민들은 ‘영종하늘대교’를 주장하며 반발했다.... ",
			"pubDate":"Sun, 07 Sep 2025 07:11:00 +0900"
		},
		{
			"title":"인천 구월동 '트레이더스 구월점'·청주 '코스트코 청주점' 소비자들 '활...",
			"originallink":"https:\/\/www.gukjenews.com\/news\/articleView.html?idxno=3369324",
			"link":"https:\/\/www.gukjenews.com\/news\/articleView.html?idxno=3369324",
			"description":"2024년 8월 21일 개점한 코스트코 <b>청라<\/b>점 전경. 사진=인천경제자유구역청 인천 구월동 '트레이더스 구월점', 청주 '코스트코 청주점' 입점 소식에 소비자들이 환호하고 있다. 인천 남동구 구월동 대형마트(매소홀로 759)... ",
			"pubDate":"Sun, 07 Sep 2025 00:20:00 +0900"
		},
		{
			"title":"가을바람 따라 떠나는 '9월의 축제' 4선 [여행 PICK]",
			"originallink":"https:\/\/www.econovill.com\/news\/articleView.html?idxno=709653",
			"link":"https:\/\/www.econovill.com\/news\/articleView.html?idxno=709653",
			"description":"일시 : 2025.9.21.(일) 주소 : 인천광역시 서구 <b>청라<\/b>대로 88 <b>청라<\/b>국제도시 야외음악당 서산 해미읍성 축제 - 전통과 현대가 어우러진 문화 축제 ▶ 성곽을 감도는 바람에서 전통과 오늘을 함께하고 싶을 때 해미읍성은 조선... ",
			"pubDate":"Sat, 06 Sep 2025 21:20:00 +0900"
		},
		{
			"title":"[김태우의 쓱크랩북] 전문가 모두가 SSG 탈락 예상했는데, 왜 야구를 잘...",
			"originallink":"https:\/\/www.spotvnews.co.kr\/news\/articleView.html?idxno=768716",
			"link":"https:\/\/m.sports.naver.com\/kbaseball\/article\/477\/0000567702",
			"description":"정리했고, 또 잘하는 선수는 실력 이상의 플러스 알파를 챙겨주며 지금까지 왔다. 전력에서 보이지 않는 무형적인 이 요소를 <b>청라<\/b> 시대로 끌고 갈 수 있다면, 이것 또한 돈으로 사지 못할 엄청난 가치일 수 있다. \/SSG 담당기자",
			"pubDate":"Sat, 06 Sep 2025 16:36:00 +0900"
		},
		{
			"title":"2년 연속 1000만 관중→역대 최다 관중 신기록→누적 2억 명까지…KBO리...",
			"originallink":"https:\/\/www.spotvnews.co.kr\/news\/articleView.html?idxno=768695",
			"link":"https:\/\/m.sports.naver.com\/kbaseball\/article\/477\/0000567691",
			"description":"2025시즌 개장한 대전 구장을 비롯해 대부분의 구장이 2014년 이후 개장했으며, 잠실, 사직, <b>청라<\/b>에도 신구장 건축이 예정되어 있어, 팬들의 관람 환경은 더욱 편리하고 팬 친화적으로 개선될 것으로 기대된다. 야구... ",
			"pubDate":"Sat, 06 Sep 2025 12:41:00 +0900"
		},
		{
			"title":"“로봇은 파업 안하잖아”…‘노란봉투법’ 등 노동쟁의 리스크에 ‘활...",
			"originallink":"https:\/\/biz.heraldcorp.com\/article\/10569835?ref=naver",
			"link":"https:\/\/n.news.naver.com\/mnews\/article\/016\/0002525013?sid=101",
			"description":"현대무벡스 <b>청라<\/b>R&amp;D센터에서 무인이송로봇(AGV) 시연이 이뤄지고 있다. [현대무벡스 제공] 이 밖에도 국내 증시 전문가들은 정부가 최근 피지컬 인공지능(AI)에 대한 투자에 적극 나서고 있다는 점을 로봇·스마트팩토리... ",
			"pubDate":"Sat, 06 Sep 2025 12:13:00 +0900"
		},
		{
			"title":"유정복 인천시장, 시민의 시민에 의한 시민을 위한 행보",
			"originallink":"http:\/\/www.lawissue.co.kr\/view.php?ud=202509061131025904d94aa4ada6_12",
			"link":"http:\/\/www.lawissue.co.kr\/view.php?ud=202509061131025904d94aa4ada6_12",
			"description":"제3연륙교 통행료 무료화, 영종·<b>청라<\/b> 교통망 개선, 원도심 재생과 균형 발전 정책 특히 ‘바다패스 정책’은 시민이 인천 연안 섬을 단돈 1,500원에 방문할 수 있도록 하고, 타 시·도 주민에게도 최대 70% 운임 할인을... ",
			"pubDate":"Sat, 06 Sep 2025 11:36:00 +0900"
		},
		{
			"title":"&quot;나가&quot;라는 소리 듣던 이숭용 감독, SSG 시즌 종료 전 재계약...재신임 ...",
			"originallink":"http:\/\/www.spochoo.com\/news\/articleView.html?idxno=113854",
			"link":"https:\/\/m.sports.naver.com\/kbaseball\/article\/529\/0000073272",
			"description":"SSG는 리빌딩 중간 성과, <b>청라<\/b>돔 시대를 향한 단계적 목표, 감독 재계약 사례 등을 종합적으로 검토해 계약 기간을 설정했음을 알렸다. 재계약의 가장 큰 배경은 역시 리빌딩 성과다. SSG 관계자는 &quot;구단의 리모델링... ",
			"pubDate":"Sat, 06 Sep 2025 10:45:00 +0900"
		},
		{
			"title":"[스타트업] &quot;K리거, AI로 아마추어 혁신&quot; 권정혁 스포잇 대표",
			"originallink":"http:\/\/www.newsprime.co.kr\/news\/article.html?no=703239",
			"link":"http:\/\/www.newsprime.co.kr\/news\/article.html?no=703239",
			"description":"기존 풋살 대관 시장에 AI 영상을 접목해 차별화를 꾀했고, 지난 9월 <b>청라<\/b> 풋볼센터에서 상업 서비스를 시작했다. 권 대표는 &quot;풋살장은 대관 수익에만 의존한다. 우리는 경기 영상을 자동 제공해 차별성을 만들고, 데이터... ",
			"pubDate":"Sat, 06 Sep 2025 10:42:00 +0900"
		},
		{
			"title":"풀무원다논, 롯데마트 문화센터와 쿠킹 클래스… &quot;그릭 요거트로 건강 ...",
			"originallink":"http:\/\/www.kdfnews.com\/news\/articleView.html?idxno=165000",
			"link":"http:\/\/www.kdfnews.com\/news\/articleView.html?idxno=165000",
			"description":"가을학기 쿠킹 클래스는 <b>청라<\/b>점을 시작으로 오는 11월 1일까지 약 3개월간 운영된다. 일정과 수강 신청은 롯데마트 문화센터 홈페이지에서 확인 가능하다. 풀무원다논 관계자는 &quot;그릭 요거트를 활용한 건강한 레시피에... ",
			"pubDate":"Sat, 06 Sep 2025 08:16:00 +0900"
		},
		{
			"title":"김찬진 인천 동구청장 “제물포구 출범…주민 목소리 경청할 것” [인터...",
			"originallink":"https:\/\/www.kyeonggi.com\/article\/20250828580219",
			"link":"https:\/\/n.news.naver.com\/mnews\/article\/666\/0000082771?sid=100",
			"description":"인천지하철 3호선은 송도, 신포동, 동인천, 송림오거리, <b>청라<\/b>, 검단을 잇는 노선이다. 동구는 기자간담회와 지속적인 건의로 동·중구 경유 구간을 우선순위에 반영하는 데 성공했다. 이는 원도심 철도 복원이라는 주민... ",
			"pubDate":"Sat, 06 Sep 2025 06:02:00 +0900"
		},
		{
			"title":"9\/6~9\/7 이마트·홈플러스·롯데마트, 휴무일·영업시간... 유통가 秋 행...",
			"originallink":"http:\/\/www.finomy.com\/news\/articleView.html?idxno=238258",
			"link":"http:\/\/www.finomy.com\/news\/articleView.html?idxno=238258",
			"description":"가좌, <b>청라<\/b>, 인천연수, 인천송도, 부천여월, 부천소사, 분당오리, 야탑, 시화, 송탄, 평택안중, 화성향남... 영종도점, <b>청라<\/b>점, 경기양평점, 광교점, 권선점, 롯데몰수지점, 수원점, 시화점, 시흥배곧점, 시흥점, 신갈점... ",
			"pubDate":"Sat, 06 Sep 2025 00:26:00 +0900"
		},
		{
			"title":"&quot;강화남단 경제자유구역·농정국 신설 시급&quot; 윤재상 시의원 강조",
			"originallink":"https:\/\/www.newscj.com\/news\/articleView.html?idxno=3314451",
			"link":"https:\/\/www.newscj.com\/news\/articleView.html?idxno=3314451",
			"description":"이에 유정복 인천시장과 인천경제자유구역청장은 &quot;송도·영종·<b>청라<\/b> 중심의 경제자유구역을 더 확대해 미래 성장 동력을 찾아야 하며, 그 적임지가 강화&quot;라며 관계부처와 협력해 나가겠다고 답했다. 이어 윤 의원은 농업... ",
			"pubDate":"Fri, 05 Sep 2025 19:50:00 +0900"
		},
		{
			"title":"[25박신자컵] “좋은 경험이 되었으면” WKBL 데뷔 무대 마친 이상범 감...",
			"originallink":"",
			"link":"https:\/\/m.sports.naver.com\/basketball\/article\/065\/0000284084",
			"description":"하나은행은 클럽하우스가 있는 <b>청라<\/b>로 이동, 두달 여가 남은 시즌 개막 준비에 박차를 가한다. 승자 DVTK는 조별 예선 2승 2패를 기록, 3위로 첫 박신자컵 일정을 마무리했다. 부천 하나은행 이상범 감독 경기 총평 정말... ",
			"pubDate":"Fri, 05 Sep 2025 19:16:00 +0900"
		},
		{
			"title":"수도권매립지 4매립장에 국가정원 조성?…관건은 매립지 종료",
			"originallink":"https:\/\/news.ifm.kr\/news\/articleView.html?idxno=451560",
			"link":"https:\/\/news.ifm.kr\/news\/articleView.html?idxno=451560",
			"description":"수도권매립지와 경인아라뱃길을 중심으로 완료 예정인 드림파크 72홀, 아시아드경기장 36홀, <b>청라<\/b> 18홀 등 126홀의 파크골프장과 아쿠아리움 등 레포츠시설·유원시설을 함께 연계하면 시너지 효과가 클 것이라는... ",
			"pubDate":"Fri, 05 Sep 2025 18:24:00 +0900"
		},
		{
			"title":"로봇·산업용·협동로봇 관련주, '봄바람' 현대무벡스·티엑스알로보틱...",
			"originallink":"http:\/\/www.finomy.com\/news\/articleView.html?idxno=238277",
			"link":"http:\/\/www.finomy.com\/news\/articleView.html?idxno=238277",
			"description":"IT서비스 부문은 시스템 구축과 운영을 담당하고 있으며, <b>청라<\/b> R&amp;D센터의 기술력과 전문 인력을 기반으로 물류 설비 설계 경험을 축적해왔다. 회사는 이를 토대로 AI와 로봇 등 고도화된 기술력 확보에 주력하며 사업... ",
			"pubDate":"Fri, 05 Sep 2025 18:10:00 +0900"
		},
		{
			"title":"IS동서, <b>청라<\/b> 주상복합단지 분양대금 반환소송 2심서 패…“69억 지급해...",
			"originallink":"http:\/\/www.g-enews.com\/ko-kr\/news\/article\/news_all\/202509051735455996ac06cade6e_1\/article.html",
			"link":"http:\/\/www.g-enews.com\/ko-kr\/news\/article\/news_all\/202509051735455996ac06cade6e_1\/article.html",
			"description":"5일 법조계에 따르면 서울고등법원 민사37-3부는 <b>청라<\/b> 센트럴 에일린의뜰 입주민 950명이 시공사인 IS동서를... IS동서는 한국토지주택공사(LH)로부터 <b>청라<\/b>지구 주상복합용지를 낙찰 받아 2015년 이 단지를 분양했다. 이... ",
			"pubDate":"Fri, 05 Sep 2025 17:38:00 +0900"
		}
	]
}