{
	"lastBuildDate":"Sat, 28 Sep 2024 20:40:02 +0900",
	"total":247601,
	"start":1,
	"display":30,
	"items":[
		{
			"title":"[STN포토]어프로치샷 하는 이소영",
			"originallink":"https:\/\/www.stnsports.co.kr\/news\/articleView.html?idxno=231678",
			"link":"https:\/\/m.sports.naver.com\/golf\/article\/450\/0000114779",
			"description":"2024 KLPGA투어 스물다섯 번째 대회인 '하나금융그룹 챔피언십'(총상금 15억 원, 우승상금 2억 7천만 원)이 오는 인천 <b>청라<\/b>에 위치한 베어즈베스트 <b>청라<\/b>(파72\/6,689야드)에서 펼쳐지고 있다. 28일 현재 3라운드... ",
			"pubDate":"Sat, 28 Sep 2024 20:38:00 +0900"
		},
		{
			"title":"[STN포토]서어진, 중요한 파 퍼트에요",
			"originallink":"https:\/\/www.stnsports.co.kr\/news\/articleView.html?idxno=231676",
			"link":"https:\/\/m.sports.naver.com\/golf\/article\/450\/0000114777",
			"description":"2024 KLPGA투어 스물다섯 번째 대회인 '하나금융그룹 챔피언십'(총상금 15억 원, 우승상금 2억 7천만 원)이 오는 인천 <b>청라<\/b>에 위치한 베어즈베스트 <b>청라<\/b>(파72\/6,689야드)에서 펼쳐지고 있다. 28일 현재 3라운드... ",
			"pubDate":"Sat, 28 Sep 2024 20:37:00 +0900"
		},
		{
			"title":"[STN포토]파세이브 성공하는 서어진",
			"originallink":"https:\/\/www.stnsports.co.kr\/news\/articleView.html?idxno=231677",
			"link":"https:\/\/m.sports.naver.com\/golf\/article\/450\/0000114778",
			"description":"2024 KLPGA투어 스물다섯 번째 대회인 '하나금융그룹 챔피언십'(총상금 15억 원, 우승상금 2억 7천만 원)이 오는 인천 <b>청라<\/b>에 위치한 베어즈베스트 <b>청라<\/b>(파72\/6,689야드)에서 펼쳐지고 있다. 28일 현재 3라운드... ",
			"pubDate":"Sat, 28 Sep 2024 20:37:00 +0900"
		},
		{
			"title":"[STN포토]파퍼트 준비하는 서어진",
			"originallink":"https:\/\/www.stnsports.co.kr\/news\/articleView.html?idxno=231675",
			"link":"https:\/\/m.sports.naver.com\/golf\/article\/450\/0000114776",
			"description":"2024 KLPGA투어 스물다섯 번째 대회인 '하나금융그룹 챔피언십'(총상금 15억 원, 우승상금 2억 7천만 원)이 오는 인천 <b>청라<\/b>에 위치한 베어즈베스트 <b>청라<\/b>(파72\/6,689야드)에서 펼쳐지고 있다. 28일 현재 3라운드... ",
			"pubDate":"Sat, 28 Sep 2024 20:36:00 +0900"
		},
		{
			"title":"[STN포토]파퍼트 조준하는 서어진",
			"originallink":"https:\/\/www.stnsports.co.kr\/news\/articleView.html?idxno=231673",
			"link":"https:\/\/m.sports.naver.com\/golf\/article\/450\/0000114774",
			"description":"2024 KLPGA투어 스물다섯 번째 대회인 '하나금융그룹 챔피언십'(총상금 15억 원, 우승상금 2억 7천만 원)이 오는 인천 <b>청라<\/b>에 위치한 베어즈베스트 <b>청라<\/b>(파72\/6,689야드)에서 펼쳐지고 있다. 28일 현재 3라운드... ",
			"pubDate":"Sat, 28 Sep 2024 20:35:00 +0900"
		},
		{
			"title":"[STN포토]파라인을 살피는 서어진",
			"originallink":"https:\/\/www.stnsports.co.kr\/news\/articleView.html?idxno=231674",
			"link":"https:\/\/m.sports.naver.com\/golf\/article\/450\/0000114775",
			"description":"2024 KLPGA투어 스물다섯 번째 대회인 '하나금융그룹 챔피언십'(총상금 15억 원, 우승상금 2억 7천만 원)이 오는 인천 <b>청라<\/b>에 위치한 베어즈베스트 <b>청라<\/b>(파72\/6,689야드)에서 펼쳐지고 있다. 28일 현재 3라운드... ",
			"pubDate":"Sat, 28 Sep 2024 20:35:00 +0900"
		},
		{
			"title":"[STN포토]세컨드샷 날리는 유현조",
			"originallink":"https:\/\/www.stnsports.co.kr\/news\/articleView.html?idxno=231672",
			"link":"https:\/\/m.sports.naver.com\/golf\/article\/450\/0000114773",
			"description":"2024 KLPGA투어 스물다섯 번째 대회인 '하나금융그룹 챔피언십'(총상금 15억 원, 우승상금 2억 7천만 원)이 오는 인천 <b>청라<\/b>에 위치한 베어즈베스트 <b>청라<\/b>(파72\/6,689야드)에서 펼쳐지고 있다. 28일 현재 3라운드... ",
			"pubDate":"Sat, 28 Sep 2024 20:34:00 +0900"
		},
		{
			"title":"[STN포토]서드샷 준비하는 서어진",
			"originallink":"https:\/\/www.stnsports.co.kr\/news\/articleView.html?idxno=231670",
			"link":"https:\/\/m.sports.naver.com\/golf\/article\/450\/0000114771",
			"description":"2024 KLPGA투어 스물다섯 번째 대회인 '하나금융그룹 챔피언십'(총상금 15억 원, 우승상금 2억 7천만 원)이 오는 인천 <b>청라<\/b>에 위치한 베어즈베스트 <b>청라<\/b>(파72\/6,689야드)에서 펼쳐지고 있다. 28일 현재 3라운드... ",
			"pubDate":"Sat, 28 Sep 2024 20:33:00 +0900"
		},
		{
			"title":"[STN포토]홀 가까이 붙이는 서어진",
			"originallink":"https:\/\/www.stnsports.co.kr\/news\/articleView.html?idxno=231671",
			"link":"https:\/\/m.sports.naver.com\/golf\/article\/450\/0000114772",
			"description":"2024 KLPGA투어 스물다섯 번째 대회인 '하나금융그룹 챔피언십'(총상금 15억 원, 우승상금 2억 7천만 원)이 오는 인천 <b>청라<\/b>에 위치한 베어즈베스트 <b>청라<\/b>(파72\/6,689야드)에서 펼쳐지고 있다. 28일 현재 3라운드... ",
			"pubDate":"Sat, 28 Sep 2024 20:33:00 +0900"
		},
		{
			"title":"[STN포토]어프로치샷 하는 서어진",
			"originallink":"https:\/\/www.stnsports.co.kr\/news\/articleView.html?idxno=231669",
			"link":"https:\/\/m.sports.naver.com\/golf\/article\/450\/0000114770",
			"description":"2024 KLPGA투어 스물다섯 번째 대회인 '하나금융그룹 챔피언십'(총상금 15억 원, 우승상금 2억 7천만 원)이 오는 인천 <b>청라<\/b>에 위치한 베어즈베스트 <b>청라<\/b>(파72\/6,689야드)에서 펼쳐지고 있다. 28일 현재 3라운드... ",
			"pubDate":"Sat, 28 Sep 2024 20:32:00 +0900"
		},
		{
			"title":"윤이나, 하나금융그룹 챔피언십 3R도 선두 수성 ‘시즌 2승 정조준’··...",
			"originallink":"https:\/\/sports.khan.co.kr\/article\/202409282030003?pt=nv",
			"link":"https:\/\/m.sports.naver.com\/golf\/article\/144\/0000991331",
			"description":"윤이나는 28일 인천 베어즈베스트 <b>청라<\/b> 골프클럽(파72·6712야드)에서 열린 대회 3라운드에서 버디 3개와 보기 3개를 맞바꿔 이븐파 72타를 쳤다. 중간합계 8언더파 208타를 써낸 윤이나는 김수지, 마다솜과 공동 선두에... ",
			"pubDate":"Sat, 28 Sep 2024 20:31:00 +0900"
		},
		{
			"title":"[STN포토]그린을 살펴보는 서어진",
			"originallink":"https:\/\/www.stnsports.co.kr\/news\/articleView.html?idxno=231668",
			"link":"https:\/\/m.sports.naver.com\/golf\/article\/450\/0000114769",
			"description":"2024 KLPGA투어 스물다섯 번째 대회인 '하나금융그룹 챔피언십'(총상금 15억 원, 우승상금 2억 7천만 원)이 오는 인천 <b>청라<\/b>에 위치한 베어즈베스트 <b>청라<\/b>(파72\/6,689야드)에서 펼쳐지고 있다. 28일 현재 3라운드... ",
			"pubDate":"Sat, 28 Sep 2024 20:31:00 +0900"
		},
		{
			"title":"[STN포토]그린으로 이동하고 있는 서어진",
			"originallink":"https:\/\/www.stnsports.co.kr\/news\/articleView.html?idxno=231667",
			"link":"https:\/\/m.sports.naver.com\/golf\/article\/450\/0000114768",
			"description":"2024 KLPGA투어 스물다섯 번째 대회인 '하나금융그룹 챔피언십'(총상금 15억 원, 우승상금 2억 7천만 원)이 오는 인천 <b>청라<\/b>에 위치한 베어즈베스트 <b>청라<\/b>(파72\/6,689야드)에서 펼쳐지고 있다. 28일 현재 3라운드... ",
			"pubDate":"Sat, 28 Sep 2024 20:30:00 +0900"
		},
		{
			"title":"[STN포토]티샷후 출발하는 리디아고",
			"originallink":"https:\/\/www.stnsports.co.kr\/news\/articleView.html?idxno=231666",
			"link":"https:\/\/m.sports.naver.com\/golf\/article\/450\/0000114767",
			"description":"2024 KLPGA투어 스물다섯 번째 대회인 '하나금융그룹 챔피언십'(총상금 15억 원, 우승상금 2억 7천만 원)이 오는 인천 <b>청라<\/b>에 위치한 베어즈베스트 <b>청라<\/b>(파72\/6,689야드)에서 펼쳐지고 있다. 28일 현재 3라운드... ",
			"pubDate":"Sat, 28 Sep 2024 20:29:00 +0900"
		},
		{
			"title":"[STN포토]강하게 티샷 날리는 리디아고",
			"originallink":"https:\/\/www.stnsports.co.kr\/news\/articleView.html?idxno=231664",
			"link":"https:\/\/m.sports.naver.com\/golf\/article\/450\/0000114765",
			"description":"2024 KLPGA투어 스물다섯 번째 대회인 '하나금융그룹 챔피언십'(총상금 15억 원, 우승상금 2억 7천만 원)이 오는 인천 <b>청라<\/b>에 위치한 베어즈베스트 <b>청라<\/b>(파72\/6,689야드)에서 펼쳐지고 있다. 28일 현재 3라운드... ",
			"pubDate":"Sat, 28 Sep 2024 20:28:00 +0900"
		},
		{
			"title":"[STN포토]티샷 방향 바라보는 리디아고",
			"originallink":"https:\/\/www.stnsports.co.kr\/news\/articleView.html?idxno=231665",
			"link":"https:\/\/m.sports.naver.com\/golf\/article\/450\/0000114766",
			"description":"2024 KLPGA투어 스물다섯 번째 대회인 '하나금융그룹 챔피언십'(총상금 15억 원, 우승상금 2억 7천만 원)이 오는 인천 <b>청라<\/b>에 위치한 베어즈베스트 <b>청라<\/b>(파72\/6,689야드)에서 펼쳐지고 있다. 28일 현재 3라운드... ",
			"pubDate":"Sat, 28 Sep 2024 20:28:00 +0900"
		},
		{
			"title":"[STN포토]티샷 방향을 조준하는 리디아고",
			"originallink":"https:\/\/www.stnsports.co.kr\/news\/articleView.html?idxno=231662",
			"link":"https:\/\/m.sports.naver.com\/golf\/article\/450\/0000114764",
			"description":"2024 KLPGA투어 스물다섯 번째 대회인 '하나금융그룹 챔피언십'(총상금 15억 원, 우승상금 2억 7천만 원)이 오는 인천 <b>청라<\/b>에 위치한 베어즈베스트 <b>청라<\/b>(파72\/6,689야드)에서 펼쳐지고 있다. 28일 현재 3라운드... ",
			"pubDate":"Sat, 28 Sep 2024 20:17:00 +0900"
		},
		{
			"title":"[STN포토]티샷 방향을 확인하는 리디아고",
			"originallink":"https:\/\/www.stnsports.co.kr\/news\/articleView.html?idxno=231661",
			"link":"https:\/\/m.sports.naver.com\/golf\/article\/450\/0000114763",
			"description":"2024 KLPGA투어 스물다섯 번째 대회인 '하나금융그룹 챔피언십'(총상금 15억 원, 우승상금 2억 7천만 원)이 오는 인천 <b>청라<\/b>에 위치한 베어즈베스트 <b>청라<\/b>(파72\/6,689야드)에서 펼쳐지고 있다. 28일 현재 3라운드... ",
			"pubDate":"Sat, 28 Sep 2024 20:16:00 +0900"
		},
		{
			"title":"[STN포토]파퍼트 기다리는 리디아고",
			"originallink":"https:\/\/www.stnsports.co.kr\/news\/articleView.html?idxno=231659",
			"link":"https:\/\/m.sports.naver.com\/golf\/article\/450\/0000114761",
			"description":"2024 KLPGA투어 스물다섯 번째 대회인 '하나금융그룹 챔피언십'(총상금 15억 원, 우승상금 2억 7천만 원)이 오는 인천 <b>청라<\/b>에 위치한 베어즈베스트 <b>청라<\/b>(파72\/6,689야드)에서 펼쳐지고 있다. 28일 현재 3라운드... ",
			"pubDate":"Sat, 28 Sep 2024 20:15:00 +0900"
		},
		{
			"title":"[STN포토]파퍼트 하고 있는 리디아고",
			"originallink":"https:\/\/www.stnsports.co.kr\/news\/articleView.html?idxno=231660",
			"link":"https:\/\/m.sports.naver.com\/golf\/article\/450\/0000114762",
			"description":"2024 KLPGA투어 스물다섯 번째 대회인 '하나금융그룹 챔피언십'(총상금 15억 원, 우승상금 2억 7천만 원)이 오는 인천 <b>청라<\/b>에 위치한 베어즈베스트 <b>청라<\/b>(파72\/6,689야드)에서 펼쳐지고 있다. 28일 현재 3라운드... ",
			"pubDate":"Sat, 28 Sep 2024 20:15:00 +0900"
		},
		{
			"title":"[STN포토]퍼트 라인을 파악하는 리디아고",
			"originallink":"https:\/\/www.stnsports.co.kr\/news\/articleView.html?idxno=231658",
			"link":"https:\/\/m.sports.naver.com\/golf\/article\/450\/0000114760",
			"description":"2024 KLPGA투어 스물다섯 번째 대회인 '하나금융그룹 챔피언십'(총상금 15억 원, 우승상금 2억 7천만 원)이 오는 인천 <b>청라<\/b>에 위치한 베어즈베스트 <b>청라<\/b>(파72\/6,689야드)에서 펼쳐지고 있다. 28일 현재 3라운드... ",
			"pubDate":"Sat, 28 Sep 2024 20:14:00 +0900"
		},
		{
			"title":"[STN포토]그린 상태를 파악하는 리디나고",
			"originallink":"https:\/\/www.stnsports.co.kr\/news\/articleView.html?idxno=231656",
			"link":"https:\/\/m.sports.naver.com\/golf\/article\/450\/0000114758",
			"description":"2024 KLPGA투어 스물다섯 번째 대회인 '하나금융그룹 챔피언십'(총상금 15억 원, 우승상금 2억 7천만 원)이 오는 인천 <b>청라<\/b>에 위치한 베어즈베스트 <b>청라<\/b>(파72\/6,689야드)에서 펼쳐지고 있다. 28일 현재 3라운드... ",
			"pubDate":"Sat, 28 Sep 2024 20:13:00 +0900"
		},
		{
			"title":"[STN포토]어프로치샷 하는 리디아고",
			"originallink":"https:\/\/www.stnsports.co.kr\/news\/articleView.html?idxno=231657",
			"link":"https:\/\/m.sports.naver.com\/golf\/article\/450\/0000114759",
			"description":"2024 KLPGA투어 스물다섯 번째 대회인 '하나금융그룹 챔피언십'(총상금 15억 원, 우승상금 2억 7천만 원)이 오는 인천 <b>청라<\/b>에 위치한 베어즈베스트 <b>청라<\/b>(파72\/6,689야드)에서 펼쳐지고 있다. 28일 현재 3라운드... ",
			"pubDate":"Sat, 28 Sep 2024 20:13:00 +0900"
		},
		{
			"title":"[STN포토]그린으로 이동하는 리디아고",
			"originallink":"https:\/\/www.stnsports.co.kr\/news\/articleView.html?idxno=231655",
			"link":"https:\/\/m.sports.naver.com\/golf\/article\/450\/0000114757",
			"description":"2024 KLPGA투어 스물다섯 번째 대회인 '하나금융그룹 챔피언십'(총상금 15억 원, 우승상금 2억 7천만 원)이 오는 인천 <b>청라<\/b>에 위치한 베어즈베스트 <b>청라<\/b>(파72\/6,689야드)에서 펼쳐지고 있다. 28일 현재 3라운드... ",
			"pubDate":"Sat, 28 Sep 2024 20:12:00 +0900"
		},
		{
			"title":"[STN포토]강하게 티샷 보내는 노승희",
			"originallink":"https:\/\/www.stnsports.co.kr\/news\/articleView.html?idxno=231653",
			"link":"https:\/\/m.sports.naver.com\/golf\/article\/450\/0000114755",
			"description":"2024 KLPGA투어 스물다섯 번째 대회인 '하나금융그룹 챔피언십'(총상금 15억 원, 우승상금 2억 7천만 원)이 오는 인천 <b>청라<\/b>에 위치한 베어즈베스트 <b>청라<\/b>(파72\/6,689야드)에서 펼쳐지고 있다. 28일 현재 3라운드... ",
			"pubDate":"Sat, 28 Sep 2024 20:11:00 +0900"
		},
		{
			"title":"[STN포토]타샷 방향을 바라보는 노승희",
			"originallink":"https:\/\/www.stnsports.co.kr\/news\/articleView.html?idxno=231654",
			"link":"https:\/\/m.sports.naver.com\/golf\/article\/450\/0000114756",
			"description":"2024 KLPGA투어 스물다섯 번째 대회인 '하나금융그룹 챔피언십'(총상금 15억 원, 우승상금 2억 7천만 원)이 오는 인천 <b>청라<\/b>에 위치한 베어즈베스트 <b>청라<\/b>(파72\/6,689야드)에서 펼쳐지고 있다. 28일 현재 3라운드... ",
			"pubDate":"Sat, 28 Sep 2024 20:11:00 +0900"
		},
		{
			"title":"[STN포토]티샷 방향을 조준하는 노승희",
			"originallink":"https:\/\/www.stnsports.co.kr\/news\/articleView.html?idxno=231652",
			"link":"https:\/\/m.sports.naver.com\/golf\/article\/450\/0000114754",
			"description":"2024 KLPGA투어 스물다섯 번째 대회인 '하나금융그룹 챔피언십'(총상금 15억 원, 우승상금 2억 7천만 원)이 오는 인천 <b>청라<\/b>에 위치한 베어즈베스트 <b>청라<\/b>(파72\/6,689야드)에서 펼쳐지고 있다. 28일 현재 3라운드... ",
			"pubDate":"Sat, 28 Sep 2024 20:07:00 +0900"
		},
		{
			"title":"[STN포토]브이 날리며 이동하는 노승희",
			"originallink":"https:\/\/www.stnsports.co.kr\/news\/articleView.html?idxno=231650",
			"link":"https:\/\/m.sports.naver.com\/golf\/article\/450\/0000114753",
			"description":"2024 KLPGA투어 스물다섯 번째 대회인 '하나금융그룹 챔피언십'(총상금 15억 원, 우승상금 2억 7천만 원)이 오는 인천 <b>청라<\/b>에 위치한 베어즈베스트 <b>청라<\/b>(파72\/6,689야드)에서 펼쳐지고 있다. 28일 현재 3라운드... ",
			"pubDate":"Sat, 28 Sep 2024 20:04:00 +0900"
		},
		{
			"title":"[STN포토]버디퍼트 준비하는 노승희",
			"originallink":"https:\/\/www.stnsports.co.kr\/news\/articleView.html?idxno=231648",
			"link":"https:\/\/m.sports.naver.com\/golf\/article\/450\/0000114751",
			"description":"2024 KLPGA투어 스물다섯 번째 대회인 '하나금융그룹 챔피언십'(총상금 15억 원, 우승상금 2억 7천만 원)이 오는 인천 <b>청라<\/b>에 위치한 베어즈베스트 <b>청라<\/b>(파72\/6,689야드)에서 펼쳐지고 있다. 28일 현재 3라운드... ",
			"pubDate":"Sat, 28 Sep 2024 20:03:00 +0900"
		},
		{
			"title":"[STN포토]파퍼트 기다리는 노승희",
			"originallink":"https:\/\/www.stnsports.co.kr\/news\/articleView.html?idxno=231649",
			"link":"https:\/\/m.sports.naver.com\/golf\/article\/450\/0000114752",
			"description":"2024 KLPGA투어 스물다섯 번째 대회인 '하나금융그룹 챔피언십'(총상금 15억 원, 우승상금 2억 7천만 원)이 오는 인천 <b>청라<\/b>에 위치한 베어즈베스트 <b>청라<\/b>(파72\/6,689야드)에서 펼쳐지고 있다. 28일 현재 3라운드... ",
			"pubDate":"Sat, 28 Sep 2024 20:03:00 +0900"
		}
	]
}