[{"apartDong":"청라동","apartName":"청라더샵레이크파크","dealDay":"09","apartAddress":"154-1","dealYear":"2014","dealFloor":"57","apartCreatedYear":"2013","dealUpdated":"2020-02-12","apartSize":"188.504","apartCityCode":"28260","id":18510,"dealMoney":"136,010","dealMonth":"04"},{"apartDong":"청라동","apartName":"청라 SK VIEW","dealDay":"29","apartAddress":"103-16","dealYear":"2015","dealFloor":"29","apartCreatedYear":"2011","dealUpdated":"2020-02-12","apartSize":"212.9522","apartCityCode":"28260","id":30824,"dealMoney":"122,500","dealMonth":"08"},{"apartDong":"청라동","apartName":"청라더샵레이크파크","dealDay":"21","apartAddress":"154-1","dealYear":"2019","dealFloor":"40","apartCreatedYear":"2013","dealUpdated":"2020-02-12","apartSize":"137.224","apartCityCode":"28260","id":58580,"dealMoney":"116,000","dealMonth":"12"},{"apartDong":"청라동","apartName":"청라국제금융단지한양수자인레이크블루","dealDay":"04","apartAddress":"85-1","dealYear":"2019","dealFloor":"28","apartCreatedYear":"2019","dealUpdated":"2020-02-12","apartSize":"124.451","apartCityCode":"28260","id":56171,"dealMoney":"106,000","dealMonth":"09"},{"apartDong":"청라동","apartName":"대우푸르지오","dealDay":"11","apartAddress":"150-1","dealYear":"2019","dealFloor":"44","apartCreatedYear":"2013","dealUpdated":"2020-02-12","apartSize":"139.486","apartCityCode":"28260","id":57599,"dealMoney":"102,000","dealMonth":"11"},{"apartDong":"청라동","apartName":"청라자이","dealDay":"19","apartAddress":"193-1","dealYear":"2015","dealFloor":"19","apartCreatedYear":"2010","dealUpdated":"2020-02-12","apartSize":"216.1166","apartCityCode":"28260","id":32585,"dealMoney":"100,000","dealMonth":"11"},{"apartDong":"청라동","apartName":"대우푸르지오","dealDay":"31","apartAddress":"150-1","dealYear":"2019","dealFloor":"35","apartCreatedYear":"2013","dealUpdated":"2020-02-12","apartSize":"114.104","apartCityCode":"28260","id":58685,"dealMoney":"89,000","dealMonth":"12"},{"apartDong":"청라동","apartName":"대우푸르지오","dealDay":"05","apartAddress":"150-1","dealYear":"2019","dealFloor":"28","apartCreatedYear":"2013","dealUpdated":"2020-02-12","apartSize":"120.315","apartCityCode":"28260","id":57547,"dealMoney":"86,250","dealMonth":"11"},{"apartDong":"청라동","apartName":"청라더샵레이크파크","dealDay":"11","apartAddress":"154-1","dealYear":"2020","dealFloor":"36","apartCreatedYear":"2013","dealUpdated":"2020-02-12","apartSize":"106.893","apartCityCode":"28260","id":59279,"dealMoney":"83,500","dealMonth":"01"},{"apartDong":"청라동","apartName":"한라비발디","dealDay":"07","apartAddress":"107-1","dealYear":"2020","dealFloor":"22","apartCreatedYear":"2011","dealUpdated":"2020-02-12","apartSize":"133.8597","apartCityCode":"28260","id":59228,"dealMoney":"82,500","dealMonth":"01"},{"apartDong":"청라동","apartName":"청라 한화 꿈에그린","dealDay":"09","apartAddress":"139-1","dealYear":"2019","dealFloor":"26","apartCreatedYear":"2012","dealUpdated":"2020-02-12","apartSize":"136.3519","apartCityCode":"28260","id":56189,"dealMoney":"81,500","dealMonth":"09"},{"apartDong":"청라동","apartName":"엑슬루타워","dealDay":"05","apartAddress":"164-1","dealYear":"2014","dealFloor":"49","apartCreatedYear":"2011","dealUpdated":"2020-02-12","apartSize":"150.28","apartCityCode":"28260","id":17888,"dealMoney":"77,100","dealMonth":"03"},{"apartDong":"청라동","apartName":"청라 한화 꿈에그린","dealDay":"04","apartAddress":"139-1","dealYear":"2020","dealFloor":"20","apartCreatedYear":"2012","dealUpdated":"2020-02-12","apartSize":"125.6483","apartCityCode":"28260","id":59589,"dealMoney":"77,000","dealMonth":"02"},{"apartDong":"청라동","apartName":"청라롯데캐슬","dealDay":"20","apartAddress":"159-1","dealYear":"2017","dealFloor":"36","apartCreatedYear":"2013","dealUpdated":"2020-02-12","apartSize":"141.1803","apartCityCode":"28260","id":43879,"dealMoney":"76,000","dealMonth":"07"},{"apartDong":"청라동","apartName":"청라 SK VIEW","dealDay":"12","apartAddress":"103-16","dealYear":"2019","dealFloor":"26","apartCreatedYear":"2011","dealUpdated":"2020-02-12","apartSize":"128.7778","apartCityCode":"28260","id":58435,"dealMoney":"75,000","dealMonth":"12"},{"apartDong":"청라동","apartName":"청라더샵레이크파크","dealDay":"09","apartAddress":"154-1","dealYear":"2020","dealFloor":"19","apartCreatedYear":"2013","dealUpdated":"2020-02-12","apartSize":"100.59","apartCityCode":"28260","id":59245,"dealMoney":"75,000","dealMonth":"01"},{"apartDong":"청라동","apartName":"대우푸르지오","dealDay":"13","apartAddress":"150-1","dealYear":"2020","dealFloor":"17","apartCreatedYear":"2013","dealUpdated":"2020-02-13","apartSize":"94.741","apartCityCode":"28260","id":59658,"dealMoney":"74,900","dealMonth":"01"},{"apartDong":"청라동","apartName":"청라웰카운티19단지","dealDay":"03","apartAddress":"166-1","dealYear":"2020","dealFloor":"24","apartCreatedYear":"2012","dealUpdated":"2020-02-12","apartSize":"146.84","apartCityCode":"28260","id":59578,"dealMoney":"74,700","dealMonth":"02"},{"apartDong":"청라동","apartName":"청라 SK VIEW","dealDay":"21","apartAddress":"103-16","dealYear":"2019","dealFloor":"29","apartCreatedYear":"2011","dealUpdated":"2020-02-12","apartSize":"126.775","apartCityCode":"28260","id":58569,"dealMoney":"73,000","dealMonth":"12"},{"apartDong":"청라동","apartName":"청라린스트라우스","dealDay":"22","apartAddress":"160-1","dealYear":"2020","dealFloor":"33","apartCreatedYear":"2013","dealUpdated":"2020-02-12","apartSize":"138.8445","apartCityCode":"28260","id":59440,"dealMoney":"73,000","dealMonth":"01"},{"apartDong":"청라동","apartName":"대우푸르지오","dealDay":"11","apartAddress":"150-1","dealYear":"2020","dealFloor":"28","apartCreatedYear":"2013","dealUpdated":"2020-02-12","apartSize":"94.919","apartCityCode":"28260","id":59299,"dealMoney":"70,000","dealMonth":"01"},{"apartDong":"청라동","apartName":"청라린스트라우스","dealDay":"10","apartAddress":"160-1","dealYear":"2020","dealFloor":"17","apartCreatedYear":"2013","dealUpdated":"2020-02-12","apartSize":"125.0755","apartCityCode":"28260","id":59620,"dealMoney":"70,000","dealMonth":"02"},{"apartDong":"청라동","apartName":"한라비발디","dealDay":"29","apartAddress":"107-1","dealYear":"2019","dealFloor":"23","apartCreatedYear":"2011","dealUpdated":"2020-02-12","apartSize":"133.9686","apartCityCode":"28260","id":54695,"dealMoney":"70,000","dealMonth":"06"},{"apartDong":"청라동","apartName":"청라린스트라우스","dealDay":"03","apartAddress":"160-1","dealYear":"2020","dealFloor":"15","apartCreatedYear":"2013","dealUpdated":"2020-02-12","apartSize":"124.4115","apartCityCode":"28260","id":59583,"dealMoney":"69,000","dealMonth":"02"},{"apartDong":"청라동","apartName":"청라제일풍경채2차에듀앤파크","dealDay":"15","apartAddress":"149-2","dealYear":"2020","dealFloor":"14","apartCreatedYear":"2017","dealUpdated":"2020-02-12","apartSize":"99.764","apartCityCode":"28260","id":59339,"dealMoney":"69,300","dealMonth":"01"},{"apartDong":"청라동","apartName":"한라비발디","dealDay":"01","apartAddress":"107-1","dealYear":"2020","dealFloor":"7","apartCreatedYear":"2011","dealUpdated":"2020-02-12","apartSize":"113.9149","apartCityCode":"28260","id":59566,"dealMoney":"69,000","dealMonth":"02"},{"apartDong":"청라동","apartName":"청라자이","dealDay":"01","apartAddress":"193-1","dealYear":"2011","dealFloor":"9","apartCreatedYear":"2010","dealUpdated":"2020-02-12","apartSize":"142.8738","apartCityCode":"28260","id":2010,"dealMoney":"68,420","dealMonth":"02"},{"apartDong":"청라동","apartName":"청라제일풍경채2차에듀앤파크","dealDay":"01","apartAddress":"149-2","dealYear":"2020","dealFloor":"18","apartCreatedYear":"2017","dealUpdated":"2020-02-12","apartSize":"84.846","apartCityCode":"28260","id":59567,"dealMoney":"68,000","dealMonth":"02"},{"apartDong":"청라동","apartName":"청라국제금융단지한양수자인레이크블루","dealDay":"27","apartAddress":"85-1","dealYear":"2019","dealFloor":"10","apartCreatedYear":"2019","dealUpdated":"2020-02-12","apartSize":"84.3477","apartCityCode":"28260","id":56250,"dealMoney":"67,000","dealMonth":"09"},{"apartDong":"청라동","apartName":"엑슬루타워","dealDay":"24","apartAddress":"164-1","dealYear":"2012","dealFloor":"35","apartCreatedYear":"2011","dealUpdated":"2020-02-12","apartSize":"132.68","apartCityCode":"28260","id":6887,"dealMoney":"66,400","dealMonth":"09"},{"apartDong":"청라동","apartName":"청라더샵레이크파크","dealDay":"03","apartAddress":"154-1","dealYear":"2018","dealFloor":"41","apartCreatedYear":"2013","dealUpdated":"2020-02-12","apartSize":"107.106","apartCityCode":"28260","id":47900,"dealMoney":"66,500","dealMonth":"03"},{"apartDong":"청라동","apartName":"청라지구중흥S-CLASS1단지","dealDay":"29","apartAddress":"762-2","dealYear":"2015","dealFloor":"12","apartCreatedYear":"2010","dealUpdated":"2020-02-12","apartSize":"138.0543","apartCityCode":"28260","id":28043,"dealMoney":"66,456","dealMonth":"04"},{"apartDong":"청라동","apartName":"청라지구중흥S-CLASS1단지","dealDay":"04","apartAddress":"762-2","dealYear":"2015","dealFloor":"24","apartCreatedYear":"2010","dealUpdated":"2020-02-12","apartSize":"140.3317","apartCityCode":"28260","id":29415,"dealMoney":"66,456","dealMonth":"06"},{"apartDong":"청라동","apartName":"청라 SK VIEW","dealDay":"01","apartAddress":"103-16","dealYear":"2020","dealFloor":"20","apartCreatedYear":"2011","dealUpdated":"2020-02-12","apartSize":"116.8673","apartCityCode":"28260","id":59573,"dealMoney":"65,000","dealMonth":"02"},{"apartDong":"청라동","apartName":"청라 한화 꿈에그린","dealDay":"29","apartAddress":"139-1","dealYear":"2019","dealFloor":"27","apartCreatedYear":"2012","dealUpdated":"2020-02-12","apartSize":"113.7267","apartCityCode":"28260","id":57799,"dealMoney":"65,000","dealMonth":"11"},{"apartDong":"청라동","apartName":"청라롯데캐슬","dealDay":"07","apartAddress":"159-1","dealYear":"2020","dealFloor":"13","apartCreatedYear":"2013","dealUpdated":"2020-02-12","apartSize":"127.12","apartCityCode":"28260","id":59219,"dealMoney":"65,000","dealMonth":"01"},{"apartDong":"청라동","apartName":"청라센트럴에일린의뜰","dealDay":"31","apartAddress":"156-1","dealYear":"2020","dealFloor":"14","apartCreatedYear":"2018","dealUpdated":"2020-02-12","apartSize":"84.961","apartCityCode":"28260","id":59506,"dealMoney":"65,000","dealMonth":"01"},{"apartDong":"청라동","apartName":"청라센트럴에일린의뜰","dealDay":"29","apartAddress":"156-1","dealYear":"2019","dealFloor":"28","apartCreatedYear":"2018","dealUpdated":"2020-02-12","apartSize":"84.9834","apartCityCode":"28260","id":57790,"dealMoney":"65,000","dealMonth":"11"},{"apartDong":"청라동","apartName":"청라제일풍경채2차에듀앤파크","dealDay":"08","apartAddress":"149-2","dealYear":"2020","dealFloor":"15","apartCreatedYear":"2017","dealUpdated":"2020-02-12","apartSize":"84.993","apartCityCode":"28260","id":59621,"dealMoney":"65,600","dealMonth":"02"},{"apartDong":"청라동","apartName":"청라지구중흥S-CLASS2단지","dealDay":"12","apartAddress":"165-13","dealYear":"2014","dealFloor":"6","apartCreatedYear":"2010","dealUpdated":"2020-02-12","apartSize":"140.334","apartCityCode":"28260","id":19040,"dealMoney":"65,291","dealMonth":"05"},{"apartDong":"청라동","apartName":"청라 SK VIEW","dealDay":"02","apartAddress":"103-16","dealYear":"2020","dealFloor":"28","apartCreatedYear":"2011","dealUpdated":"2020-02-12","apartSize":"125.4899","apartCityCode":"28260","id":59166,"dealMoney":"64,500","dealMonth":"01"},{"apartDong":"청라동","apartName":"청라센트럴에일린의뜰","dealDay":"04","apartAddress":"156-1","dealYear":"2020","dealFloor":"29","apartCreatedYear":"2018","dealUpdated":"2020-02-12","apartSize":"84.9704","apartCityCode":"28260","id":59181,"dealMoney":"64,900","dealMonth":"01"},{"apartDong":"청라동","apartName":"청라센트럴에일린의뜰","dealDay":"21","apartAddress":"156-1","dealYear":"2019","dealFloor":"8","apartCreatedYear":"2018","dealUpdated":"2020-02-12","apartSize":"95.2717","apartCityCode":"28260","id":58579,"dealMoney":"64,000","dealMonth":"12"},{"apartDong":"청라동","apartName":"청라국제금융단지한양수자인레이크블루","dealDay":"07","apartAddress":"85-1","dealYear":"2019","dealFloor":"33","apartCreatedYear":"2019","dealUpdated":"2020-02-12","apartSize":"84.3971","apartCityCode":"28260","id":55131,"dealMoney":"63,400","dealMonth":"07"},{"apartDong":"청라동","apartName":"청라동문굿모닝힐","dealDay":"26","apartAddress":"102-10","dealYear":"2019","dealFloor":"30","apartCreatedYear":"2012","dealUpdated":"2020-02-12","apartSize":"125.586","apartCityCode":"28260","id":58621,"dealMoney":"63,500","dealMonth":"12"},{"apartDong":"청라동","apartName":"청라롯데캐슬","dealDay":"10","apartAddress":"159-1","dealYear":"2020","dealFloor":"38","apartCreatedYear":"2013","dealUpdated":"2020-02-12","apartSize":"125.6244","apartCityCode":"28260","id":59263,"dealMoney":"63,000","dealMonth":"01"},{"apartDong":"청라동","apartName":"청라지구중흥S-CLASS2단지","dealDay":"10","apartAddress":"165-13","dealYear":"2014","dealFloor":"15","apartCreatedYear":"2010","dealUpdated":"2020-02-12","apartSize":"141.3898","apartCityCode":"28260","id":23957,"dealMoney":"63,501","dealMonth":"12"},{"apartDong":"청라동","apartName":"청라지구중흥S-CLASS2단지","dealDay":"30","apartAddress":"165-13","dealYear":"2014","dealFloor":"15","apartCreatedYear":"2010","dealUpdated":"2020-02-12","apartSize":"141.4386","apartCityCode":"28260","id":24081,"dealMoney":"63,501","dealMonth":"12"},{"apartDong":"청라동","apartName":"청라29블럭호반베르디움","dealDay":"26","apartAddress":"970-1","dealYear":"2019","dealFloor":"10","apartCreatedYear":"2012","dealUpdated":"2020-02-13","apartSize":"84.9482","apartCityCode":"28260","id":59628,"dealMoney":"62,500","dealMonth":"12"},{"apartDong":"청라동","apartName":"청라롯데캐슬","dealDay":"19","apartAddress":"159-1","dealYear":"2020","dealFloor":"15","apartCreatedYear":"2013","dealUpdated":"2020-02-12","apartSize":"113.7568","apartCityCode":"28260","id":59395,"dealMoney":"62,600","dealMonth":"01"},{"apartDong":"청라동","apartName":"청라지구중흥S-CLASS1단지","dealDay":"21","apartAddress":"762-2","dealYear":"2014","dealFloor":"1","apartCreatedYear":"2010","dealUpdated":"2020-02-12","apartSize":"139.2117","apartCityCode":"28260","id":20216,"dealMoney":"62,456","dealMonth":"07"},{"apartDong":"청라동","apartName":"엑슬루타워","dealDay":"20","apartAddress":"164-1","dealYear":"2013","dealFloor":"53","apartCreatedYear":"2011","dealUpdated":"2020-02-12","apartSize":"110.22","apartCityCode":"28260","id":11100,"dealMoney":"60,200","dealMonth":"06"},{"apartDong":"청라동","apartName":"청라29블럭호반베르디움","dealDay":"21","apartAddress":"970-1","dealYear":"2019","dealFloor":"23","apartCreatedYear":"2012","dealUpdated":"2020-02-12","apartSize":"84.9289","apartCityCode":"28260","id":58578,"dealMoney":"60,000","dealMonth":"12"},{"apartDong":"청라동","apartName":"청라29블럭호반베르디움","dealDay":"21","apartAddress":"970-1","dealYear":"2019","dealFloor":"29","apartCreatedYear":"2012","dealUpdated":"2020-02-12","apartSize":"84.9934","apartCityCode":"28260","id":58583,"dealMoney":"60,000","dealMonth":"12"},{"apartDong":"청라동","apartName":"청라골드클래스커낼웨이","dealDay":"09","apartAddress":"165-7","dealYear":"2020","dealFloor":"12","apartCreatedYear":"2016","dealUpdated":"2020-02-12","apartSize":"82.9214","apartCityCode":"28260","id":59247,"dealMoney":"60,000","dealMonth":"01"},{"apartDong":"청라동","apartName":"청라린스트라우스","dealDay":"18","apartAddress":"160-1","dealYear":"2020","dealFloor":"14","apartCreatedYear":"2013","dealUpdated":"2020-02-12","apartSize":"101.9819","apartCityCode":"28260","id":59372,"dealMoney":"60,000","dealMonth":"01"},{"apartDong":"청라동","apartName":"하우스토리","dealDay":"16","apartAddress":"155-2","dealYear":"2016","dealFloor":"15","apartCreatedYear":"2011","dealUpdated":"2020-02-12","apartSize":"124.209","apartCityCode":"28260","id":40434,"dealMoney":"60,000","dealMonth":"12"},{"apartDong":"청라동","apartName":"청라 한화 꿈에그린","dealDay":"19","apartAddress":"139-1","dealYear":"2020","dealFloor":"17","apartCreatedYear":"2012","dealUpdated":"2020-02-12","apartSize":"100.5108","apartCityCode":"28260","id":59398,"dealMoney":"59,000","dealMonth":"01"},{"apartDong":"청라동","apartName":"청라 한화 꿈에그린","dealDay":"28","apartAddress":"139-1","dealYear":"2019","dealFloor":"22","apartCreatedYear":"2012","dealUpdated":"2020-02-12","apartSize":"113.7584","apartCityCode":"28260","id":56260,"dealMoney":"59,500","dealMonth":"09"},{"apartDong":"청라동","apartName":"청라국제 업무단지 센텀 대광로제비앙","dealDay":"04","apartAddress":"83-1","dealYear":"2020","dealFloor":"22","apartCreatedYear":"2018","dealUpdated":"2020-02-12","apartSize":"82.6715","apartCityCode":"28260","id":59202,"dealMoney":"59,500","dealMonth":"01"},{"apartDong":"청라동","apartName":"청라국제 업무단지 센텀 대광로제비앙","dealDay":"04","apartAddress":"83-1","dealYear":"2020","dealFloor":"8","apartCreatedYear":"2018","dealUpdated":"2020-02-12","apartSize":"82.9117","apartCityCode":"28260","id":59203,"dealMoney":"59,800","dealMonth":"01"},{"apartDong":"청라동","apartName":"청라제일풍경채2차에듀앤파크","dealDay":"03","apartAddress":"149-2","dealYear":"2020","dealFloor":"18","apartCreatedYear":"2017","dealUpdated":"2020-02-13","apartSize":"74.29","apartCityCode":"28260","id":59681,"dealMoney":"59,000","dealMonth":"02"},{"apartDong":"청라동","apartName":"청라제일풍경채2차에듀앤파크","dealDay":"28","apartAddress":"149-2","dealYear":"2019","dealFloor":"25","apartCreatedYear":"2017","dealUpdated":"2020-02-12","apartSize":"84.939","apartCityCode":"28260","id":58643,"dealMoney":"59,800","dealMonth":"12"},{"apartDong":"청라동","apartName":"한라비발디","dealDay":"26","apartAddress":"107-1","dealYear":"2019","dealFloor":"16","apartCreatedYear":"2011","dealUpdated":"2020-02-12","apartSize":"113.6765","apartCityCode":"28260","id":58627,"dealMoney":"59,500","dealMonth":"12"},{"apartDong":"청라동","apartName":"한일베라체","dealDay":"04","apartAddress":"155-9","dealYear":"2020","dealFloor":"12","apartCreatedYear":"2011","dealUpdated":"2020-02-12","apartSize":"122.785","apartCityCode":"28260","id":59588,"dealMoney":"59,000","dealMonth":"02"},{"apartDong":"청라동","apartName":"NPART","dealDay":"10","apartAddress":"155-12","dealYear":"2020","dealFloor":"14","apartCreatedYear":"2011","dealUpdated":"2020-02-12","apartSize":"117.9506","apartCityCode":"28260","id":59251,"dealMoney":"58,000","dealMonth":"01"},{"apartDong":"청라동","apartName":"청라 한화 꿈에그린","dealDay":"31","apartAddress":"139-1","dealYear":"2019","dealFloor":"16","apartCreatedYear":"2012","dealUpdated":"2020-02-12","apartSize":"100.7927","apartCityCode":"28260","id":58684,"dealMoney":"58,850","dealMonth":"12"},{"apartDong":"청라동","apartName":"청라제일풍경채","dealDay":"15","apartAddress":"115-1","dealYear":"2012","dealFloor":"10","apartCreatedYear":"2012","dealUpdated":"2020-02-12","apartSize":"134.1428","apartCityCode":"28260","id":7357,"dealMoney":"58,770","dealMonth":"10"},{"apartDong":"청라동","apartName":"청라힐스테이트커낼뷰","dealDay":"26","apartAddress":"155-17","dealYear":"2019","dealFloor":"11","apartCreatedYear":"2012","dealUpdated":"2020-02-12","apartSize":"121.285","apartCityCode":"28260","id":58628,"dealMoney":"58,000","dealMonth":"12"},{"apartDong":"청라동","apartName":"청라힐스테이트커낼뷰","dealDay":"10","apartAddress":"155-17","dealYear":"2019","dealFloor":"11","apartCreatedYear":"2012","dealUpdated":"2020-02-12","apartSize":"121.313","apartCityCode":"28260","id":55664,"dealMoney":"58,500","dealMonth":"08"},{"apartDong":"청라동","apartName":"청라자이","dealDay":"19","apartAddress":"193-1","dealYear":"2011","dealFloor":"9","apartCreatedYear":"2010","dealUpdated":"2020-02-12","apartSize":"114.0091","apartCityCode":"28260","id":2336,"dealMoney":"57,720","dealMonth":"03"},{"apartDong":"청라동","apartName":"청라지구중흥S-CLASS1단지","dealDay":"31","apartAddress":"762-2","dealYear":"2014","dealFloor":"12","apartCreatedYear":"2010","dealUpdated":"2020-02-12","apartSize":"119.5876","apartCityCode":"28260","id":22964,"dealMoney":"57,180","dealMonth":"10"},{"apartDong":"청라동","apartName":"청라지구중흥S-CLASS1단지","dealDay":"15","apartAddress":"762-2","dealYear":"2016","dealFloor":"12","apartCreatedYear":"2010","dealUpdated":"2020-02-12","apartSize":"120.4555","apartCityCode":"28260","id":40081,"dealMoney":"57,180","dealMonth":"11"},{"apartDong":"청라동","apartName":"청라한양수자인","dealDay":"10","apartAddress":"102-2","dealYear":"2016","dealFloor":"26","apartCreatedYear":"2011","dealUpdated":"2020-02-12","apartSize":"142.9247","apartCityCode":"28260","id":38638,"dealMoney":"57,800","dealMonth":"09"},{"apartDong":"청라동","apartName":"청라 SK VIEW","dealDay":"10","apartAddress":"103-16","dealYear":"2020","dealFloor":"9","apartCreatedYear":"2011","dealUpdated":"2020-02-12","apartSize":"115.0253","apartCityCode":"28260","id":59259,"dealMoney":"56,000","dealMonth":"01"},{"apartDong":"청라동","apartName":"청라동문굿모닝힐","dealDay":"22","apartAddress":"102-10","dealYear":"2020","dealFloor":"24","apartCreatedYear":"2012","dealUpdated":"2020-02-12","apartSize":"125.129","apartCityCode":"28260","id":59449,"dealMoney":"56,000","dealMonth":"01"},{"apartDong":"청라동","apartName":"청라린스트라우스","dealDay":"11","apartAddress":"160-1","dealYear":"2019","dealFloor":"23","apartCreatedYear":"2013","dealUpdated":"2020-02-12","apartSize":"101.3622","apartCityCode":"28260","id":58430,"dealMoney":"56,000","dealMonth":"12"},{"apartDong":"청라동","apartName":"청라힐스테이트커낼뷰","dealDay":"13","apartAddress":"155-17","dealYear":"2020","dealFloor":"14","apartCreatedYear":"2012","dealUpdated":"2020-02-12","apartSize":"121.308","apartCityCode":"28260","id":59316,"dealMoney":"56,500","dealMonth":"01"},{"apartDong":"청라동","apartName":"한일베라체","dealDay":"27","apartAddress":"155-9","dealYear":"2012","dealFloor":"11","apartCreatedYear":"2011","dealUpdated":"2020-02-12","apartSize":"139.687","apartCityCode":"28260","id":5138,"dealMoney":"56,589","dealMonth":"02"},{"apartDong":"청라동","apartName":"청라 SK VIEW","dealDay":"31","apartAddress":"103-16","dealYear":"2019","dealFloor":"20","apartCreatedYear":"2011","dealUpdated":"2020-02-12","apartSize":"101.5882","apartCityCode":"28260","id":58686,"dealMoney":"55,000","dealMonth":"12"},{"apartDong":"청라동","apartName":"청라 SK VIEW","dealDay":"30","apartAddress":"103-16","dealYear":"2019","dealFloor":"11","apartCreatedYear":"2011","dealUpdated":"2020-02-12","apartSize":"114.3812","apartCityCode":"28260","id":57817,"dealMoney":"55,000","dealMonth":"11"},{"apartDong":"청라동","apartName":"청라 한화 꿈에그린","dealDay":"16","apartAddress":"139-1","dealYear":"2019","dealFloor":"17","apartCreatedYear":"2012","dealUpdated":"2020-02-12","apartSize":"112.9319","apartCityCode":"28260","id":58502,"dealMoney":"55,000","dealMonth":"12"},{"apartDong":"청라동","apartName":"청라국제 업무단지 센텀 대광로제비앙","dealDay":"14","apartAddress":"83-1","dealYear":"2019","dealFloor":"23","apartCreatedYear":"2018","dealUpdated":"2020-02-12","apartSize":"82.8228","apartCityCode":"28260","id":58469,"dealMoney":"55,000","dealMonth":"12"},{"apartDong":"청라동","apartName":"청라동양엔파트","dealDay":"22","apartAddress":"102-3","dealYear":"2020","dealFloor":"26","apartCreatedYear":"2012","dealUpdated":"2020-02-12","apartSize":"118.3699","apartCityCode":"28260","id":59434,"dealMoney":"55,000","dealMonth":"01"},{"apartDong":"청라동","apartName":"청라모아미래도","dealDay":"02","apartAddress":"82-1","dealYear":"2020","dealFloor":"8","apartCreatedYear":"2018","dealUpdated":"2020-02-12","apartSize":"71.3679","apartCityCode":"28260","id":59159,"dealMoney":"55,000","dealMonth":"01"},{"apartDong":"청라동","apartName":"청라반도유보라","dealDay":"05","apartAddress":"103-26","dealYear":"2020","dealFloor":"14","apartCreatedYear":"2011","dealUpdated":"2020-02-12","apartSize":"126.0777","apartCityCode":"28260","id":59600,"dealMoney":"55,000","dealMonth":"02"},{"apartDong":"청라동","apartName":"청라반도유보라2.0","dealDay":"23","apartAddress":"102-16","dealYear":"2020","dealFloor":"17","apartCreatedYear":"2012","dealUpdated":"2020-02-12","apartSize":"121.7338","apartCityCode":"28260","id":59450,"dealMoney":"55,000","dealMonth":"01"},{"apartDong":"청라동","apartName":"청라웰카운티19단지","dealDay":"02","apartAddress":"166-1","dealYear":"2014","dealFloor":"8","apartCreatedYear":"2012","dealUpdated":"2020-02-12","apartSize":"146.35","apartCityCode":"28260","id":20143,"dealMoney":"55,000","dealMonth":"07"},{"apartDong":"청라동","apartName":"청라제일풍경채","dealDay":"20","apartAddress":"115-1","dealYear":"2020","dealFloor":"12","apartCreatedYear":"2012","dealUpdated":"2020-02-12","apartSize":"115.1067","apartCityCode":"28260","id":59407,"dealMoney":"55,000","dealMonth":"01"},{"apartDong":"청라동","apartName":"청라제일풍경채","dealDay":"21","apartAddress":"115-1","dealYear":"2018","dealFloor":"2","apartCreatedYear":"2012","dealUpdated":"2020-02-12","apartSize":"115.9895","apartCityCode":"28260","id":49180,"dealMoney":"55,000","dealMonth":"06"},{"apartDong":"청라동","apartName":"청라한양수자인","dealDay":"16","apartAddress":"102-2","dealYear":"2020","dealFloor":"21","apartCreatedYear":"2011","dealUpdated":"2020-02-12","apartSize":"121.4449","apartCityCode":"28260","id":59348,"dealMoney":"55,000","dealMonth":"01"},{"apartDong":"청라동","apartName":"NPART","dealDay":"27","apartAddress":"155-12","dealYear":"2020","dealFloor":"7","apartCreatedYear":"2011","dealUpdated":"2020-02-12","apartSize":"118.1682","apartCityCode":"28260","id":59474,"dealMoney":"54,700","dealMonth":"01"},{"apartDong":"청라동","apartName":"청라동양엔파트","dealDay":"04","apartAddress":"102-3","dealYear":"2020","dealFloor":"26","apartCreatedYear":"2012","dealUpdated":"2020-02-12","apartSize":"118.8352","apartCityCode":"28260","id":59585,"dealMoney":"54,500","dealMonth":"02"},{"apartDong":"청라동","apartName":"청라반도유보라2.0","dealDay":"04","apartAddress":"102-16","dealYear":"2020","dealFloor":"7","apartCreatedYear":"2012","dealUpdated":"2020-02-12","apartSize":"101.9953","apartCityCode":"28260","id":59590,"dealMoney":"54,000","dealMonth":"02"},{"apartDong":"청라동","apartName":"청라웰카운티19단지","dealDay":"30","apartAddress":"166-1","dealYear":"2015","dealFloor":"12","apartCreatedYear":"2012","dealUpdated":"2020-02-12","apartSize":"124.82","apartCityCode":"28260","id":32620,"dealMoney":"54,750","dealMonth":"11"},{"apartDong":"청라동","apartName":"한라비발디","dealDay":"28","apartAddress":"107-1","dealYear":"2019","dealFloor":"13","apartCreatedYear":"2011","dealUpdated":"2020-02-12","apartSize":"113.6697","apartCityCode":"28260","id":58641,"dealMoney":"54,000","dealMonth":"12"},{"apartDong":"청라동","apartName":"청라29블럭호반베르디움","dealDay":"22","apartAddress":"970-1","dealYear":"2020","dealFloor":"7","apartCreatedYear":"2012","dealUpdated":"2020-02-12","apartSize":"84.9382","apartCityCode":"28260","id":59438,"dealMoney":"53,000","dealMonth":"01"},{"apartDong":"청라동","apartName":"청라동문굿모닝힐","dealDay":"12","apartAddress":"102-10","dealYear":"2016","dealFloor":"26","apartCreatedYear":"2012","dealUpdated":"2020-02-12","apartSize":"114.453","apartCityCode":"28260","id":40421,"dealMoney":"53,900","dealMonth":"12"},{"apartDong":"청라동","apartName":"청라웰카운티19단지","dealDay":"20","apartAddress":"166-1","dealYear":"2020","dealFloor":"18","apartCreatedYear":"2012","dealUpdated":"2020-02-12","apartSize":"110.63","apartCityCode":"28260","id":59408,"dealMoney":"53,000","dealMonth":"01"},{"apartDong":"청라동","apartName":"청라자이","dealDay":"29","apartAddress":"193-1","dealYear":"2020","dealFloor":"9","apartCreatedYear":"2010","dealUpdated":"2020-02-12","apartSize":"115.5101","apartCityCode":"28260","id":59485,"dealMoney":"53,000","dealMonth":"01"},{"apartDong":"청라동","apartName":"청라제일풍경채","dealDay":"28","apartAddress":"115-1","dealYear":"2020","dealFloor":"6","apartCreatedYear":"2012","dealUpdated":"2020-02-12","apartSize":"115.133","apartCityCode":"28260","id":59481,"dealMoney":"53,500","dealMonth":"01"},{"apartDong":"청라동","apartName":"하우스토리","dealDay":"29","apartAddress":"155-2","dealYear":"2020","dealFloor":"12","apartCreatedYear":"2011","dealUpdated":"2020-02-12","apartSize":"105.867","apartCityCode":"28260","id":59489,"dealMoney":"53,000","dealMonth":"01"},{"apartDong":"청라동","apartName":"NPART","dealDay":"10","apartAddress":"155-12","dealYear":"2018","dealFloor":"13","apartCreatedYear":"2011","dealUpdated":"2020-02-12","apartSize":"117.9017","apartCityCode":"28260","id":51414,"dealMoney":"52,300","dealMonth":"10"},{"apartDong":"청라동","apartName":"청라 SK VIEW","dealDay":"03","apartAddress":"103-16","dealYear":"2020","dealFloor":"8","apartCreatedYear":"2011","dealUpdated":"2020-02-12","apartSize":"101.6409","apartCityCode":"28260","id":59170,"dealMoney":"52,000","dealMonth":"01"},{"apartDong":"청라동","apartName":"청라반도유보라","dealDay":"08","apartAddress":"103-26","dealYear":"2020","dealFloor":"10","apartCreatedYear":"2011","dealUpdated":"2020-02-12","apartSize":"101.957","apartCityCode":"28260","id":59615,"dealMoney":"52,000","dealMonth":"02"},{"apartDong":"청라동","apartName":"청라웰카운티19단지","dealDay":"22","apartAddress":"166-1","dealYear":"2014","dealFloor":"26","apartCreatedYear":"2012","dealUpdated":"2020-02-12","apartSize":"162.11","apartCityCode":"28260","id":17209,"dealMoney":"52,000","dealMonth":"02"},{"apartDong":"청라동","apartName":"청라제일풍경채","dealDay":"03","apartAddress":"115-1","dealYear":"2020","dealFloor":"10","apartCreatedYear":"2012","dealUpdated":"2020-02-12","apartSize":"101.9669","apartCityCode":"28260","id":59579,"dealMoney":"52,600","dealMonth":"02"},{"apartDong":"청라동","apartName":"청라제일풍경채","dealDay":"24","apartAddress":"115-1","dealYear":"2020","dealFloor":"7","apartCreatedYear":"2012","dealUpdated":"2020-02-12","apartSize":"101.9831","apartCityCode":"28260","id":59469,"dealMoney":"52,500","dealMonth":"01"},{"apartDong":"청라동","apartName":"한라비발디","dealDay":"02","apartAddress":"107-1","dealYear":"2020","dealFloor":"13","apartCreatedYear":"2011","dealUpdated":"2020-02-12","apartSize":"101.7327","apartCityCode":"28260","id":59164,"dealMoney":"52,000","dealMonth":"01"},{"apartDong":"청라동","apartName":"호반베르디움(116-6)","dealDay":"19","apartAddress":"116-6","dealYear":"2020","dealFloor":"25","apartCreatedYear":"2011","dealUpdated":"2020-02-12","apartSize":"84.9925","apartCityCode":"28260","id":59400,"dealMoney":"52,500","dealMonth":"01"},{"apartDong":"청라동","apartName":"엑슬루타워","dealDay":"29","apartAddress":"164-1","dealYear":"2014","dealFloor":"55","apartCreatedYear":"2011","dealUpdated":"2020-02-12","apartSize":"102.62","apartCityCode":"28260","id":15181,"dealMoney":"51,403","dealMonth":"01"},{"apartDong":"청라동","apartName":"청라동양엔파트","dealDay":"18","apartAddress":"102-3","dealYear":"2020","dealFloor":"14","apartCreatedYear":"2012","dealUpdated":"2020-02-12","apartSize":"118.3573","apartCityCode":"28260","id":59394,"dealMoney":"51,000","dealMonth":"01"},{"apartDong":"청라동","apartName":"청라모아미래도","dealDay":"01","apartAddress":"82-1","dealYear":"2020","dealFloor":"4","apartCreatedYear":"2018","dealUpdated":"2020-02-12","apartSize":"71.0928","apartCityCode":"28260","id":59157,"dealMoney":"51,000","dealMonth":"01"},{"apartDong":"청라동","apartName":"청라모아미래도","dealDay":"19","apartAddress":"82-1","dealYear":"2019","dealFloor":"11","apartCreatedYear":"2018","dealUpdated":"2020-02-12","apartSize":"71.5966","apartCityCode":"28260","id":58544,"dealMoney":"51,900","dealMonth":"12"},{"apartDong":"청라동","apartName":"청라반도유보라2.0","dealDay":"21","apartAddress":"102-16","dealYear":"2020","dealFloor":"14","apartCreatedYear":"2012","dealUpdated":"2020-02-12","apartSize":"101.9765","apartCityCode":"28260","id":59427,"dealMoney":"51,000","dealMonth":"01"},{"apartDong":"청라동","apartName":"한라비발디","dealDay":"11","apartAddress":"107-1","dealYear":"2020","dealFloor":"20","apartCreatedYear":"2011","dealUpdated":"2020-02-12","apartSize":"101.981","apartCityCode":"28260","id":59286,"dealMoney":"51,500","dealMonth":"01"},{"apartDong":"청라동","apartName":"청라국제금융단지한양수자인레이크블루","dealDay":"21","apartAddress":"85-1","dealYear":"2019","dealFloor":"30","apartCreatedYear":"2019","dealUpdated":"2020-02-12","apartSize":"84.424","apartCityCode":"28260","id":52955,"dealMoney":"50,480","dealMonth":"02"},{"apartDong":"청라동","apartName":"청라동문굿모닝힐","dealDay":"13","apartAddress":"102-10","dealYear":"2020","dealFloor":"9","apartCreatedYear":"2012","dealUpdated":"2020-02-12","apartSize":"114.53","apartCityCode":"28260","id":59312,"dealMoney":"50,000","dealMonth":"01"},{"apartDong":"청라동","apartName":"청라동양엔파트","dealDay":"30","apartAddress":"102-3","dealYear":"2012","dealFloor":"8","apartCreatedYear":"2012","dealUpdated":"2020-02-12","apartSize":"118.8376","apartCityCode":"28260","id":7750,"dealMoney":"50,000","dealMonth":"11"},{"apartDong":"청라동","apartName":"청라웰카운티19단지","dealDay":"27","apartAddress":"166-1","dealYear":"2017","dealFloor":"19","apartCreatedYear":"2012","dealUpdated":"2020-02-12","apartSize":"97.26","apartCityCode":"28260","id":42106,"dealMoney":"50,498","dealMonth":"04"},{"apartDong":"청라동","apartName":"청라자이","dealDay":"09","apartAddress":"193-1","dealYear":"2010","dealFloor":"2","apartCreatedYear":"2010","dealUpdated":"2020-02-12","apartSize":"101.9088","apartCityCode":"28260","id":1017,"dealMoney":"50,000","dealMonth":"11"},{"apartDong":"청라동","apartName":"청라자이","dealDay":"28","apartAddress":"193-1","dealYear":"2019","dealFloor":"17","apartCreatedYear":"2010","dealUpdated":"2020-02-12","apartSize":"114.79","apartCityCode":"28260","id":58639,"dealMoney":"50,000","dealMonth":"12"},{"apartDong":"청라동","apartName":"청라자이","dealDay":"16","apartAddress":"193-1","dealYear":"2019","dealFloor":"7","apartCreatedYear":"2010","dealUpdated":"2020-02-12","apartSize":"114.9285","apartCityCode":"28260","id":57662,"dealMoney":"50,000","dealMonth":"11"},{"apartDong":"청라동","apartName":"청라한양수자인","dealDay":"18","apartAddress":"102-2","dealYear":"2015","dealFloor":"23","apartCreatedYear":"2011","dealUpdated":"2020-02-12","apartSize":"120.207","apartCityCode":"28260","id":28729,"dealMoney":"50,500","dealMonth":"05"},{"apartDong":"청라동","apartName":"호반베르디움","dealDay":"28","apartAddress":"168-1","dealYear":"2019","dealFloor":"30","apartCreatedYear":"2011","dealUpdated":"2020-02-12","apartSize":"84.8385","apartCityCode":"28260","id":57788,"dealMoney":"50,000","dealMonth":"11"},{"apartDong":"청라동","apartName":"청라동양엔파트","dealDay":"11","apartAddress":"102-3","dealYear":"2020","dealFloor":"20","apartCreatedYear":"2012","dealUpdated":"2020-02-12","apartSize":"118.8538","apartCityCode":"28260","id":59297,"dealMoney":"49,800","dealMonth":"01"},{"apartDong":"청라동","apartName":"청라웰카운티19단지","dealDay":"30","apartAddress":"166-1","dealYear":"2019","dealFloor":"17","apartCreatedYear":"2012","dealUpdated":"2020-02-12","apartSize":"120.2","apartCityCode":"28260","id":57811,"dealMoney":"49,900","dealMonth":"11"},{"apartDong":"청라동","apartName":"청라웰카운티19단지","dealDay":"26","apartAddress":"166-1","dealYear":"2019","dealFloor":"22","apartCreatedYear":"2012","dealUpdated":"2020-02-12","apartSize":"120.72","apartCityCode":"28260","id":55717,"dealMoney":"49,500","dealMonth":"08"},{"apartDong":"청라동","apartName":"한일베라체","dealDay":"25","apartAddress":"155-9","dealYear":"2018","dealFloor":"1","apartCreatedYear":"2011","dealUpdated":"2020-02-12","apartSize":"135.222","apartCityCode":"28260","id":48398,"dealMoney":"49,000","dealMonth":"04"},{"apartDong":"청라동","apartName":"한일베라체","dealDay":"27","apartAddress":"155-9","dealYear":"2016","dealFloor":"10","apartCreatedYear":"2011","dealUpdated":"2020-02-12","apartSize":"139.451","apartCityCode":"28260","id":37618,"dealMoney":"49,000","dealMonth":"08"},{"apartDong":"청라동","apartName":"호반베르디움","dealDay":"15","apartAddress":"168-1","dealYear":"2019","dealFloor":"30","apartCreatedYear":"2011","dealUpdated":"2020-02-12","apartSize":"84.852","apartCityCode":"28260","id":58489,"dealMoney":"49,500","dealMonth":"12"},{"apartDong":"청라동","apartName":"호반베르디움","dealDay":"12","apartAddress":"168-1","dealYear":"2019","dealFloor":"30","apartCreatedYear":"2011","dealUpdated":"2020-02-12","apartSize":"84.9207","apartCityCode":"28260","id":58431,"dealMoney":"49,000","dealMonth":"12"},{"apartDong":"청라동","apartName":"호반베르디움(116-6)","dealDay":"01","apartAddress":"116-6","dealYear":"2020","dealFloor":"29","apartCreatedYear":"2011","dealUpdated":"2020-02-12","apartSize":"84.9589","apartCityCode":"28260","id":59560,"dealMoney":"49,500","dealMonth":"02"},{"apartDong":"청라동","apartName":"NPART","dealDay":"13","apartAddress":"155-12","dealYear":"2019","dealFloor":"3","apartCreatedYear":"2011","dealUpdated":"2020-02-12","apartSize":"117.8648","apartCityCode":"28260","id":57625,"dealMoney":"48,200","dealMonth":"11"},{"apartDong":"청라동","apartName":"NPART","dealDay":"26","apartAddress":"155-12","dealYear":"2018","dealFloor":"12","apartCreatedYear":"2011","dealUpdated":"2020-02-12","apartSize":"117.9428","apartCityCode":"28260","id":49192,"dealMoney":"48,800","dealMonth":"06"},{"apartDong":"청라동","apartName":"엑슬루타워","dealDay":"08","apartAddress":"164-1","dealYear":"2020","dealFloor":"50","apartCreatedYear":"2011","dealUpdated":"2020-02-12","apartSize":"92.43","apartCityCode":"28260","id":59616,"dealMoney":"48,000","dealMonth":"02"},{"apartDong":"청라동","apartName":"청라국제금융단지한양수자인레이크블루","dealDay":"31","apartAddress":"85-1","dealYear":"2019","dealFloor":"10","apartCreatedYear":"2019","dealUpdated":"2020-02-12","apartSize":"84.4945","apartCityCode":"28260","id":54286,"dealMoney":"48,000","dealMonth":"05"},{"apartDong":"청라동","apartName":"청라우미린","dealDay":"12","apartAddress":"103-6","dealYear":"2019","dealFloor":"22","apartCreatedYear":"2011","dealUpdated":"2020-02-12","apartSize":"84.964","apartCityCode":"28260","id":58432,"dealMoney":"48,300","dealMonth":"12"},{"apartDong":"청라동","apartName":"청라자이","dealDay":"22","apartAddress":"193-1","dealYear":"2019","dealFloor":"5","apartCreatedYear":"2010","dealUpdated":"2020-02-12","apartSize":"114.8126","apartCityCode":"28260","id":54681,"dealMoney":"48,700","dealMonth":"06"},{"apartDong":"청라동","apartName":"청라힐스테이트","dealDay":"16","apartAddress":"103-27","dealYear":"2020","dealFloor":"15","apartCreatedYear":"2012","dealUpdated":"2020-02-12","apartSize":"84.982","apartCityCode":"28260","id":59352,"dealMoney":"48,000","dealMonth":"01"},{"apartDong":"청라동","apartName":"청라골드클래스","dealDay":"30","apartAddress":"103-2","dealYear":"2019","dealFloor":"14","apartCreatedYear":"2012","dealUpdated":"2020-02-12","apartSize":"116.4914","apartCityCode":"28260","id":57815,"dealMoney":"47,750","dealMonth":"11"},{"apartDong":"청라동","apartName":"한일베라체","dealDay":"10","apartAddress":"155-9","dealYear":"2020","dealFloor":"13","apartCreatedYear":"2011","dealUpdated":"2020-02-12","apartSize":"104.376","apartCityCode":"28260","id":59261,"dealMoney":"47,500","dealMonth":"01"},{"apartDong":"청라동","apartName":"NPART","dealDay":"08","apartAddress":"155-12","dealYear":"2019","dealFloor":"7","apartCreatedYear":"2011","dealUpdated":"2020-02-12","apartSize":"117.7544","apartCityCode":"28260","id":54630,"dealMoney":"46,800","dealMonth":"06"},{"apartDong":"청라동","apartName":"청라골드클래스","dealDay":"24","apartAddress":"103-2","dealYear":"2019","dealFloor":"20","apartCreatedYear":"2012","dealUpdated":"2020-02-12","apartSize":"117.1169","apartCityCode":"28260","id":58609,"dealMoney":"46,700","dealMonth":"12"},{"apartDong":"청라동","apartName":"청라지구17단지웰카운티","dealDay":"05","apartAddress":"130-2","dealYear":"2020","dealFloor":"20","apartCreatedYear":"2010","dealUpdated":"2020-02-12","apartSize":"84.4963","apartCityCode":"28260","id":59593,"dealMoney":"46,000","dealMonth":"02"},{"apartDong":"청라동","apartName":"청라우미린","dealDay":"13","apartAddress":"103-6","dealYear":"2019","dealFloor":"18","apartCreatedYear":"2011","dealUpdated":"2020-02-12","apartSize":"84.9507","apartCityCode":"28260","id":57627,"dealMoney":"45,000","dealMonth":"11"},{"apartDong":"청라동","apartName":"청라자이","dealDay":"30","apartAddress":"193-1","dealYear":"2019","dealFloor":"7","apartCreatedYear":"2010","dealUpdated":"2020-02-12","apartSize":"95.958","apartCityCode":"28260","id":55741,"dealMoney":"45,000","dealMonth":"08"},{"apartDong":"청라동","apartName":"청라반도유보라","dealDay":"02","apartAddress":"103-26","dealYear":"2019","dealFloor":"14","apartCreatedYear":"2011","dealUpdated":"2020-02-12","apartSize":"101.9597","apartCityCode":"28260","id":58334,"dealMoney":"44,000","dealMonth":"12"},{"apartDong":"청라동","apartName":"청라자이","dealDay":"05","apartAddress":"193-1","dealYear":"2019","dealFloor":"10","apartCreatedYear":"2010","dealUpdated":"2020-02-12","apartSize":"96.1614","apartCityCode":"28260","id":56874,"dealMoney":"44,000","dealMonth":"10"},{"apartDong":"청라동","apartName":"청라한양수자인","dealDay":"23","apartAddress":"102-2","dealYear":"2019","dealFloor":"23","apartCreatedYear":"2011","dealUpdated":"2020-02-12","apartSize":"102.5591","apartCityCode":"28260","id":58593,"dealMoney":"44,800","dealMonth":"12"},{"apartDong":"청라동","apartName":"청라힐스테이트","dealDay":"25","apartAddress":"103-27","dealYear":"2019","dealFloor":"5","apartCreatedYear":"2012","dealUpdated":"2020-02-12","apartSize":"84.977","apartCityCode":"28260","id":58615,"dealMoney":"44,000","dealMonth":"12"},{"apartDong":"청라동","apartName":"청라국제금융단지한양수자인레이크블루","dealDay":"19","apartAddress":"85-1","dealYear":"2019","dealFloor":"26","apartCreatedYear":"2019","dealUpdated":"2020-02-12","apartSize":"59.9849","apartCityCode":"28260","id":56946,"dealMoney":"43,000","dealMonth":"10"},{"apartDong":"청라동","apartName":"청라엘에이치","dealDay":"02","apartAddress":"184-1","dealYear":"2020","dealFloor":"8","apartCreatedYear":"2011","dealUpdated":"2020-02-12","apartSize":"84.86","apartCityCode":"28260","id":59575,"dealMoney":"43,000","dealMonth":"02"},{"apartDong":"청라동","apartName":"청라지구17단지웰카운티","dealDay":"01","apartAddress":"130-2","dealYear":"2020","dealFloor":"15","apartCreatedYear":"2010","dealUpdated":"2020-02-12","apartSize":"84.9792","apartCityCode":"28260","id":59568,"dealMoney":"43,000","dealMonth":"02"},{"apartDong":"청라동","apartName":"호반베르디움","dealDay":"04","apartAddress":"168-1","dealYear":"2020","dealFloor":"26","apartCreatedYear":"2011","dealUpdated":"2020-02-12","apartSize":"84.8324","apartCityCode":"28260","id":59205,"dealMoney":"43,300","dealMonth":"01"},{"apartDong":"청라동","apartName":"MAYLUZ","dealDay":"03","apartAddress":"165-2","dealYear":"2020","dealFloor":"10","apartCreatedYear":"2011","dealUpdated":"2020-02-12","apartSize":"83.6483","apartCityCode":"28260","id":59167,"dealMoney":"41,000","dealMonth":"01"},{"apartDong":"청라동","apartName":"서해그랑블","dealDay":"23","apartAddress":"165-10","dealYear":"2020","dealFloor":"9","apartCreatedYear":"2010","dealUpdated":"2020-02-12","apartSize":"59.9744","apartCityCode":"28260","id":59465,"dealMoney":"41,000","dealMonth":"01"},{"apartDong":"청라동","apartName":"청라우미린","dealDay":"30","apartAddress":"103-6","dealYear":"2019","dealFloor":"23","apartCreatedYear":"2011","dealUpdated":"2020-02-12","apartSize":"84.9032","apartCityCode":"28260","id":55738,"dealMoney":"41,500","dealMonth":"08"},{"apartDong":"청라동","apartName":"청라지구17단지웰카운티","dealDay":"22","apartAddress":"130-2","dealYear":"2019","dealFloor":"20","apartCreatedYear":"2010","dealUpdated":"2020-02-12","apartSize":"84.7379","apartCityCode":"28260","id":56954,"dealMoney":"41,700","dealMonth":"10"},{"apartDong":"청라동","apartName":"힐데스하임","dealDay":"01","apartAddress":"185-1","dealYear":"2020","dealFloor":"9","apartCreatedYear":"2011","dealUpdated":"2020-02-12","apartSize":"59.8871","apartCityCode":"28260","id":59557,"dealMoney":"41,000","dealMonth":"02"},{"apartDong":"청라동","apartName":"MAYLUZ","dealDay":"31","apartAddress":"165-2","dealYear":"2019","dealFloor":"6","apartCreatedYear":"2011","dealUpdated":"2020-02-12","apartSize":"81.0875","apartCityCode":"28260","id":58680,"dealMoney":"40,000","dealMonth":"12"},{"apartDong":"청라동","apartName":"MAYLUZ","dealDay":"21","apartAddress":"165-2","dealYear":"2019","dealFloor":"8","apartCreatedYear":"2011","dealUpdated":"2020-02-12","apartSize":"82.3866","apartCityCode":"28260","id":58566,"dealMoney":"40,500","dealMonth":"12"},{"apartDong":"청라동","apartName":"힐데스하임","dealDay":"31","apartAddress":"185-1","dealYear":"2020","dealFloor":"14","apartCreatedYear":"2011","dealUpdated":"2020-02-13","apartSize":"59.9435","apartCityCode":"28260","id":59664,"dealMoney":"40,600","dealMonth":"01"},{"apartDong":"청라동","apartName":"서해그랑블","dealDay":"30","apartAddress":"165-10","dealYear":"2020","dealFloor":"15","apartCreatedYear":"2010","dealUpdated":"2020-02-12","apartSize":"59.9974","apartCityCode":"28260","id":59493,"dealMoney":"39,700","dealMonth":"01"},{"apartDong":"청라동","apartName":"청라엘에이치","dealDay":"02","apartAddress":"184-1","dealYear":"2020","dealFloor":"15","apartCreatedYear":"2011","dealUpdated":"2020-02-12","apartSize":"84.96","apartCityCode":"28260","id":59161,"dealMoney":"39,300","dealMonth":"01"},{"apartDong":"청라동","apartName":"힐데스하임","dealDay":"13","apartAddress":"185-1","dealYear":"2020","dealFloor":"10","apartCreatedYear":"2011","dealUpdated":"2020-02-12","apartSize":"59.9007","apartCityCode":"28260","id":59310,"dealMoney":"39,000","dealMonth":"01"},{"apartDong":"청라동","apartName":"청라엘에이치","dealDay":"26","apartAddress":"184-1","dealYear":"2018","dealFloor":"17","apartCreatedYear":"2011","dealUpdated":"2020-02-12","apartSize":"84.81","apartCityCode":"28260","id":51519,"dealMoney":"38,000","dealMonth":"10"},{"apartDong":"청라동","apartName":"청라엘에이치","dealDay":"06","apartAddress":"184-1","dealYear":"2020","dealFloor":"7","apartCreatedYear":"2011","dealUpdated":"2020-02-12","apartSize":"74.7","apartCityCode":"28260","id":59606,"dealMoney":"36,000","dealMonth":"02"},{"apartDong":"청라동","apartName":"호반베르디움 앤 영무예다음","dealDay":"02","apartAddress":"130-4","dealYear":"2020","dealFloor":"23","apartCreatedYear":"2011","dealUpdated":"2020-02-12","apartSize":"59.738","apartCityCode":"28260","id":59576,"dealMoney":"36,000","dealMonth":"02"},{"apartDong":"청라동","apartName":"호반베르디움 앤 영무예다음","dealDay":"03","apartAddress":"130-4","dealYear":"2020","dealFloor":"26","apartCreatedYear":"2011","dealUpdated":"2020-02-12","apartSize":"59.86","apartCityCode":"28260","id":59582,"dealMoney":"35,000","dealMonth":"02"},{"apartDong":"청라동","apartName":"호반베르디움 앤 영무예다음","dealDay":"27","apartAddress":"130-4","dealYear":"2020","dealFloor":"23","apartCreatedYear":"2011","dealUpdated":"2020-02-12","apartSize":"59.936","apartCityCode":"28260","id":59471,"dealMoney":"35,000","dealMonth":"01"}]
